{"date":"2026-04-04","data":[{"name":"Octane","artist":"Don Toliver","image":"","rank":1,"last_week_rank":1,"peak_rank":0,"weeks_on_chart":8},{"name":"The Diamond Collection","artist":"Post Malone","image":"","rank":2,"last_week_rank":1,"peak_rank":0,"weeks_on_chart":101},{"name":"Take Care","artist":"Drake","image":"","rank":3,"last_week_rank":1,"peak_rank":0,"weeks_on_chart":319},{"name":"The Fall-Off","artist":"J. Cole","image":"","rank":4,"last_week_rank":1,"peak_rank":0,"weeks_on_chart":7},{"name":"Am I The Drama?","artist":"Cardi B","image":"https://charts-static.billboard.com/img/2025/10/cardi-b-tfu-amithedramaX-n71-180x180.jpg","rank":5,"last_week_rank":1,"peak_rank":0,"weeks_on_chart":27},{"name":"Views","artist":"Drake","image":"https://charts-static.billboard.com/img/2016/05/drake-bg5-views-nf7-180x180.jpg","rank":6,"last_week_rank":1,"peak_rank":0,"weeks_on_chart":246},{"name":"Curtain Call: The Hits","artist":"Eminem","image":"https://charts-static.billboard.com/img/2005/12/eminem-d78-curtaincallthehits-6on-180x180.jpg","rank":7,"last_week_rank":2,"peak_rank":0,"weeks_on_chart":315},{"name":"Certified Lover Boy","artist":"Drake","image":"https://charts-static.billboard.com/img/2021/09/drake-bg5-certifiedloverboy-6lt-180x180.jpg","rank":8,"last_week_rank":1,"peak_rank":0,"weeks_on_chart":212},{"name":"Graduation","artist":"Kanye West","image":"https://charts-static.billboard.com/img/2007/09/kanye-west-0wf-graduation-3ha-180x180.jpg","rank":9,"last_week_rank":1,"peak_rank":0,"weeks_on_chart":196},{"name":"good kid, m.A.A.d city","artist":"Kendrick Lamar","image":"https://charts-static.billboard.com/img/2012/11/kendrick-lamar-2un-goodkidmaadcity-g0t-180x180.jpg","rank":10,"last_week_rank":1,"peak_rank":0,"weeks_on_chart":362},{"name":"Greatest Hits","artist":"Pitbull","image":"https://charts-static.billboard.com/img/2017/12/pitbull-zjw-greatesthits-mgg-180x180.jpg","rank":11,"last_week_rank":9,"peak_rank":0,"weeks_on_chart":67},{"name":"GNX","artist":"Kendrick Lamar","image":"https://charts-static.billboard.com/img/2024/12/kendrick-lamar-2un-gnx-2n7-180x180.jpg","rank":12,"last_week_rank":1,"peak_rank":0,"weeks_on_chart":70},{"name":"Slime Cry","artist":"YoungBoy Never Broke Again","image":"https://charts-static.billboard.com/img/2026/01/youngboy-never-broke-again-ak3-slimecry-6v6-180x180.jpg","rank":13,"last_week_rank":2,"peak_rank":0,"weeks_on_chart":10},{"name":"Scorpion","artist":"Drake","image":"https://charts-static.billboard.com/img/2018/07/drake-bg5-scorpion-1y9-180x180.jpg","rank":14,"last_week_rank":1,"peak_rank":0,"weeks_on_chart":284},{"name":"Thank Me Later","artist":"Drake","image":"https://charts-static.billboard.com/img/2010/06/drake-bg5-thankmelater-zz6-180x180.jpg","rank":15,"last_week_rank":1,"peak_rank":0,"weeks_on_chart":97},{"name":"For All The Dogs","artist":"Drake","image":"https://charts-static.billboard.com/img/2023/10/drake-bg5-forallthedogs-w38-180x180.jpg","rank":16,"last_week_rank":1,"peak_rank":0,"weeks_on_chart":129},{"name":"My Turn","artist":"Lil Baby","image":"https://charts-static.billboard.com/img/2020/03/lilbaby-kyx-myturn-3fx-180x180.jpg","rank":17,"last_week_rank":1,"peak_rank":0,"weeks_on_chart":310},{"name":"I Hope You're Happy","artist":"BigXthaPlug","image":"https://charts-static.billboard.com/img/2025/09/bigxthaplug-b4l-ihopeyourehappy-oeq-180x180.jpg","rank":18,"last_week_rank":2,"peak_rank":0,"weeks_on_chart":31},{"name":"I Never Liked You","artist":"Future","image":"https://charts-static.billboard.com/img/2022/05/future-a0z-ineverlikedyou-m49-180x180.jpg","rank":19,"last_week_rank":1,"peak_rank":0,"weeks_on_chart":141},{"name":"DAMN.","artist":"Kendrick Lamar","image":"https://charts-static.billboard.com/img/2017/05/kendrick-lamar-2un-damn-aqz-180x180.jpg","rank":20,"last_week_rank":1,"peak_rank":0,"weeks_on_chart":293},{"name":"The Last Wun","artist":"Gunna","image":"https://charts-static.billboard.com/img/2025/08/gunna-t8f-thelastwun-zht-180x180.jpg","rank":21,"last_week_rank":1,"peak_rank":0,"weeks_on_chart":33},{"name":"2014 Forest Hills Drive","artist":"J. Cole","image":"https://charts-static.billboard.com/img/2014/12/j-cole-rta-2014foresthillsdrive-4z4-180x180.jpg","rank":22,"last_week_rank":1,"peak_rank":0,"weeks_on_chart":223},{"name":"Greatest Hits","artist":"2Pac","image":"https://charts-static.billboard.com/img/1998/12/2pac-u29-greatesthits-j5w-180x180.jpg","rank":23,"last_week_rank":11,"peak_rank":0,"weeks_on_chart":87},{"name":"Fetty Wap","artist":"Fetty Wap","image":"https://charts-static.billboard.com/img/2015/10/fetty-wap-1ev-fettywap-okn-180x180.jpg","rank":24,"last_week_rank":1,"peak_rank":0,"weeks_on_chart":63},{"name":"600 Entertainment: 6WA","artist":"BigXthaPlug & Ro$ama & Various Artists","image":"https://charts-static.billboard.com/img/2026/04/bigxthaplug-b4l-600entertainment6wa-i7b-180x180.jpg","rank":25,"last_week_rank":25,"peak_rank":0,"weeks_on_chart":1}]}