{"date":"2026-04-21","data":[{"name":"Forever","artist":"Sentury","image":"","rank":1,"last_week_rank":1,"peak_rank":0,"weeks_on_chart":30},{"name":"Fly","artist":"Tone Stith","image":"","rank":2,"last_week_rank":2,"peak_rank":0,"weeks_on_chart":10},{"name":"Folded","artist":"Kehlani","image":"","rank":3,"last_week_rank":1,"peak_rank":0,"weeks_on_chart":28},{"name":"Man I Need","artist":"Olivia Dean","image":"","rank":4,"last_week_rank":1,"peak_rank":0,"weeks_on_chart":20},{"name":"I Just Might","artist":"Bruno Mars","image":"https://charts-static.billboard.com/img/2010/01/bruno-mars-8dl-180x180.jpg","rank":5,"last_week_rank":2,"peak_rank":0,"weeks_on_chart":14},{"name":"More Than A Friend","artist":"Elijah Connor","image":"https://charts-static.billboard.com/img/2026/02/elijahconnor-000-morethanafriend-4sk-180x180.jpg","rank":6,"last_week_rank":6,"peak_rank":0,"weeks_on_chart":11},{"name":"Pressha","artist":"Jill Scott","image":"https://charts-static.billboard.com/img/2026/01/jill-scott-qci-pressha-xdk-180x180.jpg","rank":7,"last_week_rank":1,"peak_rank":0,"weeks_on_chart":14},{"name":"It Depends","artist":"Chris Brown Featuring Bryson Tiller","image":"https://charts-static.billboard.com/img/2025/08/chris-brown-t69-itdepends-6sf-180x180.jpg","rank":8,"last_week_rank":1,"peak_rank":0,"weeks_on_chart":33},{"name":"Vacancy","artist":"Ari Lennox","image":"https://charts-static.billboard.com/img/2025/10/ari-lennox-jc0-vacancy-3pi-180x180.jpg","rank":9,"last_week_rank":9,"peak_rank":0,"weeks_on_chart":22},{"name":"Bad","artist":"Saint Harison","image":"https://charts-static.billboard.com/img/2026/03/saintharison-000-bad-mmr-180x180.jpg","rank":10,"last_week_rank":10,"peak_rank":0,"weeks_on_chart":7},{"name":"Risk It All","artist":"Bruno Mars","image":"https://charts-static.billboard.com/img/2010/01/bruno-mars-8dl-180x180.jpg","rank":11,"last_week_rank":11,"peak_rank":0,"weeks_on_chart":3},{"name":"You (20th Anniversary Edition)","artist":"Raheem DeVaughn","image":"https://charts-static.billboard.com/img/2026/02/raheem-devaughn-000-you20thanniversaryedition-221-180x180.jpg","rank":12,"last_week_rank":12,"peak_rank":0,"weeks_on_chart":11},{"name":"Reclusive","artist":"Elmiene","image":"https://www.billboard.com/wp-content/themes/vip/pmc-billboard-2021/assets/public/lazyload-fallback.gif","rank":13,"last_week_rank":13,"peak_rank":0,"weeks_on_chart":8},{"name":"Let 'Em Know","artist":"T.I.","image":"https://charts-static.billboard.com/img/2026/01/ti-crc-letemknow-rv4-180x180.jpg","rank":14,"last_week_rank":14,"peak_rank":0,"weeks_on_chart":10},{"name":"You're Gonna Want Me Back","artist":"Karyn White","image":"https://charts-static.billboard.com/img/2026/01/karyn-white-000-youregonnawantmeback-r8n-180x180.jpg","rank":15,"last_week_rank":11,"peak_rank":0,"weeks_on_chart":13},{"name":"One Love","artist":"Kem","image":"https://charts-static.billboard.com/img/2026/03/kem-amn-onelove-926-180x180.jpg","rank":16,"last_week_rank":16,"peak_rank":0,"weeks_on_chart":6},{"name":"Put It On","artist":"Q Parker","image":"https://www.billboard.com/wp-content/themes/vip/pmc-billboard-2021/assets/public/lazyload-fallback.gif","rank":17,"last_week_rank":15,"peak_rank":0,"weeks_on_chart":12},{"name":"ASAP","artist":"Mya","image":"https://charts-static.billboard.com/img/2026/02/mya-9h8-asap-zog-180x180.jpg","rank":18,"last_week_rank":18,"peak_rank":0,"weeks_on_chart":12},{"name":"Baby","artist":"Gabriel Jacoby","image":"https://charts-static.billboard.com/img/2026/02/gabrieljacoby-000-baby-9lp-180x180.jpg","rank":19,"last_week_rank":19,"peak_rank":0,"weeks_on_chart":11},{"name":"Let Me","artist":"Victoria Monet","image":"https://charts-static.billboard.com/img/2026/04/victoria-monet-4qq-letme-b8h-180x180.jpg","rank":20,"last_week_rank":20,"peak_rank":0,"weeks_on_chart":2},{"name":"Burning Blue","artist":"Mariah The Scientist","image":"https://charts-static.billboard.com/img/2025/05/mariahthescientist-nuo-burningblue-pst-180x180.jpg","rank":21,"last_week_rank":20,"peak_rank":0,"weeks_on_chart":17},{"name":"Help Me Find My Drawlz","artist":"Tonio Armani","image":"https://charts-static.billboard.com/img/2026/02/tonioarmani-000-helpmefindmydrawlz-xy3-180x180.jpg","rank":22,"last_week_rank":22,"peak_rank":0,"weeks_on_chart":7},{"name":"Up Out & Gone","artist":"Ne-Yo","image":"https://charts-static.billboard.com/img/2026/04/ne-yo-d8a-upoutgone-r0v-180x180.jpg","rank":23,"last_week_rank":23,"peak_rank":0,"weeks_on_chart":1},{"name":"Spin","artist":"Kevin Ross","image":"https://www.billboard.com/wp-content/themes/vip/pmc-billboard-2021/assets/public/lazyload-fallback.gif","rank":24,"last_week_rank":24,"peak_rank":0,"weeks_on_chart":2},{"name":"Cozy","artist":"SWEATA","image":"https://charts-static.billboard.com/img/2026/04/sweata-000-cozy-dst-180x180.jpg","rank":25,"last_week_rank":24,"peak_rank":0,"weeks_on_chart":4},{"name":"Gitty Up","artist":"Cupid","image":"https://charts-static.billboard.com/img/2026/03/cupid-000-gittyup-wxi-180x180.jpg","rank":26,"last_week_rank":25,"peak_rank":0,"weeks_on_chart":5},{"name":"LUVAGIRL","artist":"Coco Jones","image":"https://charts-static.billboard.com/img/2026/04/coco-jones-bdo-luvagirl-fys-180x180.jpg","rank":27,"last_week_rank":27,"peak_rank":0,"weeks_on_chart":1},{"name":"Back It Up For Love","artist":"Shazam Conner","image":"https://charts-static.billboard.com/img/2026/01/shazamconner-000-backitupforlove-23n-180x180.jpg","rank":28,"last_week_rank":28,"peak_rank":0,"weeks_on_chart":13},{"name":"Selfish","artist":"KJ","image":"https://charts-static.billboard.com/img/2026/03/kj-000-selfish-oeg-180x180.jpg","rank":29,"last_week_rank":29,"peak_rank":0,"weeks_on_chart":4},{"name":"Who Knows","artist":"Daniel Caesar","image":"https://charts-static.billboard.com/img/2016/03/daniel-caesar-2qj-180x180.jpg","rank":30,"last_week_rank":27,"peak_rank":0,"weeks_on_chart":8}]}