{"date":"2026-05-11","data":[{"name":"Kehlani","artist":"Kehlani","image":"","rank":1,"last_week_rank":1,"peak_rank":0,"weeks_on_chart":1},{"name":"Swag","artist":"Justin Bieber","image":"","rank":2,"last_week_rank":1,"peak_rank":0,"weeks_on_chart":42},{"name":"Thriller","artist":"Michael Jackson","image":"","rank":3,"last_week_rank":1,"peak_rank":0,"weeks_on_chart":308},{"name":"Octane","artist":"Don Toliver","image":"","rank":4,"last_week_rank":1,"peak_rank":0,"weeks_on_chart":13},{"name":"Number Ones","artist":"Michael Jackson","image":"https://charts-static.billboard.com/img/2003/12/michael-jackson-y4h-numberones-8w4-180x180.jpg","rank":5,"last_week_rank":5,"peak_rank":0,"weeks_on_chart":49},{"name":"SOS","artist":"SZA","image":"https://charts-static.billboard.com/img/2022/12/sza-ijb-sos-0s7-180x180.jpg","rank":6,"last_week_rank":1,"peak_rank":0,"weeks_on_chart":177},{"name":"The Romantic","artist":"Bruno Mars","image":"https://charts-static.billboard.com/img/2026/03/bruno-mars-8dl-theromantic-gyh-180x180.jpg","rank":7,"last_week_rank":1,"peak_rank":0,"weeks_on_chart":9},{"name":"The Diamond Collection","artist":"Post Malone","image":"https://charts-static.billboard.com/img/2023/05/post-malone-uhe-thediamondcollection-pys-180x180.jpg","rank":8,"last_week_rank":2,"peak_rank":0,"weeks_on_chart":113},{"name":"Take Care","artist":"Drake","image":"https://charts-static.billboard.com/img/2011/12/drake-bg5-takecare-7bj-180x180.jpg","rank":9,"last_week_rank":1,"peak_rank":0,"weeks_on_chart":511},{"name":"Views","artist":"Drake","image":"https://charts-static.billboard.com/img/2016/05/drake-bg5-views-nf7-180x180.jpg","rank":10,"last_week_rank":1,"peak_rank":0,"weeks_on_chart":391},{"name":"Michael: Songs From The Motion Picture (Soundtrack)","artist":"Michael Jackson","image":"https://charts-static.billboard.com/img/2026/05/michael-jackson-y4h-michaelsongsfromthemotionpicturesoundtrack-gg7-180x180.jpg","rank":11,"last_week_rank":11,"peak_rank":0,"weeks_on_chart":1},{"name":"Graduation","artist":"Kanye West","image":"https://charts-static.billboard.com/img/2007/09/kanye-west-0wf-graduation-3ha-180x180.jpg","rank":12,"last_week_rank":1,"peak_rank":0,"weeks_on_chart":297},{"name":"$ome $exy $ongs 4 U","artist":"PARTYNEXTDOOR & Drake","image":"https://charts-static.billboard.com/img/2025/03/partynextdoor-83j-omeexyongs4u-6l7-180x180.jpg","rank":13,"last_week_rank":1,"peak_rank":0,"weeks_on_chart":63},{"name":"Blonde","artist":"Frank Ocean","image":"https://charts-static.billboard.com/img/2016/09/frank-ocean-3ku-blonde-ubc-180x180.jpg","rank":14,"last_week_rank":1,"peak_rank":0,"weeks_on_chart":213},{"name":"Bully","artist":"Ye","image":"https://charts-static.billboard.com/img/2026/04/kanye-west-0wf-bully-fnw-180x180.jpg","rank":15,"last_week_rank":1,"peak_rank":0,"weeks_on_chart":5},{"name":"Certified Lover Boy","artist":"Drake","image":"https://charts-static.billboard.com/img/2021/09/drake-bg5-certifiedloverboy-6lt-180x180.jpg","rank":16,"last_week_rank":1,"peak_rank":0,"weeks_on_chart":242},{"name":"Scorpion","artist":"Drake","image":"https://charts-static.billboard.com/img/2018/07/drake-bg5-scorpion-1y9-180x180.jpg","rank":17,"last_week_rank":1,"peak_rank":0,"weeks_on_chart":401},{"name":"ANTI","artist":"Rihanna","image":"https://charts-static.billboard.com/img/2016/02/rihanna-87k-anti-qcj-180x180.jpg","rank":18,"last_week_rank":1,"peak_rank":0,"weeks_on_chart":261},{"name":"Ctrl","artist":"SZA","image":"https://charts-static.billboard.com/img/2017/07/sza-ijb-ctrl-xqd-180x180.jpg","rank":19,"last_week_rank":2,"peak_rank":0,"weeks_on_chart":373},{"name":"Am I The Drama?","artist":"Cardi B","image":"https://charts-static.billboard.com/img/2025/10/cardi-b-tfu-amithedramaX-n71-180x180.jpg","rank":20,"last_week_rank":1,"peak_rank":0,"weeks_on_chart":32}]}