{"date":"2026-06-16","data":[{"name":"OKAY!","artist":"Forrest Frank","image":"","rank":1,"last_week_rank":1,"peak_rank":0,"weeks_on_chart":6},{"name":"God I'm Just Grateful","artist":"Elevation Worship & Chandler Moore","image":"","rank":2,"last_week_rank":1,"peak_rank":0,"weeks_on_chart":30},{"name":"Good Day","artist":"Forrest Frank","image":"","rank":3,"last_week_rank":1,"peak_rank":0,"weeks_on_chart":106},{"name":"Make It Well","artist":"MercyMe","image":"","rank":4,"last_week_rank":1,"peak_rank":0,"weeks_on_chart":19},{"name":"Your Way's Better","artist":"Forrest Frank","image":"https://charts-static.billboard.com/img/2023/02/forrestfrank-6cw-180x180.jpg","rank":5,"last_week_rank":1,"peak_rank":0,"weeks_on_chart":61},{"name":"Jesus Is Alive!","artist":"Forrest Frank","image":"https://charts-static.billboard.com/img/2026/05/forrestfrank-6cw-jesusisalive-50f-180x180.jpg","rank":6,"last_week_rank":1,"peak_rank":0,"weeks_on_chart":5},{"name":"Demons","artist":"Josiah Queen","image":"https://charts-static.billboard.com/img/2026/01/josiahqueen-bgh-demons-s0w-180x180.jpg","rank":7,"last_week_rank":2,"peak_rank":0,"weeks_on_chart":17},{"name":"Thankful","artist":"Forrest Frank","image":"https://charts-static.billboard.com/img/2025/12/forrestfrank-6cw-thankful-fkp-180x180.jpg","rank":8,"last_week_rank":1,"peak_rank":0,"weeks_on_chart":13},{"name":"Goodness Of God","artist":"CeCe Winans","image":"https://charts-static.billboard.com/img/1985/01/cece-winans-a1b-180x180.jpg","rank":9,"last_week_rank":1,"peak_rank":0,"weeks_on_chart":208},{"name":"Left It In The River","artist":"Jamie MacDonald","image":"https://charts-static.billboard.com/img/2025/08/jamiemacdonald-uka-leftitintheriver-4dw-180x180.jpg","rank":10,"last_week_rank":1,"peak_rank":0,"weeks_on_chart":38},{"name":"Washed","artist":"ELEVATION RHYTHM","image":"https://charts-static.billboard.com/img/2026/06/elevationrhythm-mwx-washed-o21-180x180.jpg","rank":11,"last_week_rank":11,"peak_rank":0,"weeks_on_chart":1},{"name":"Praise","artist":"Elevation Worship Featuring Brandon Lake, Chris Brown & Chandler Moore","image":"https://charts-static.billboard.com/img/2023/06/elevation-worship-efo-praise-gwp-180x180.jpg","rank":12,"last_week_rank":1,"peak_rank":0,"weeks_on_chart":125},{"name":"The Author","artist":"Brandon Lake & Nick Jonas","image":"https://charts-static.billboard.com/img/2026/05/brandonlake-j1t-theauthor-moi-180x180.jpg","rank":13,"last_week_rank":1,"peak_rank":0,"weeks_on_chart":6},{"name":"Lemonade","artist":"Forrest Frank & The Figs","image":"https://charts-static.billboard.com/img/2025/08/forrestfrank-6cw-lemonade-930-180x180.jpg","rank":14,"last_week_rank":1,"peak_rank":0,"weeks_on_chart":12},{"name":"Celebration","artist":"Forrest Frank","image":"https://charts-static.billboard.com/img/2025/05/forrestfrank-6cw-celebration-6yj-180x180.jpg","rank":15,"last_week_rank":3,"peak_rank":0,"weeks_on_chart":5}]}