{"date":"2026-06-12","data":[{"name":"Dinner Party","artist":"Niall Horan","image":"","rank":1,"last_week_rank":1,"peak_rank":0,"weeks_on_chart":1},{"name":"Sanctuary","artist":"Evanescence","image":"","rank":2,"last_week_rank":2,"peak_rank":0,"weeks_on_chart":1},{"name":"Do That Again","artist":"Malcolm Todd","image":"","rank":3,"last_week_rank":3,"peak_rank":0,"weeks_on_chart":1},{"name":"The Art Of Loving","artist":"Olivia Dean","image":"","rank":4,"last_week_rank":1,"peak_rank":0,"weeks_on_chart":37},{"name":"ICEMAN","artist":"Drake","image":"https://charts-static.billboard.com/img/2026/05/drake-v3o-iceman-s2k-180x180.jpg","rank":5,"last_week_rank":1,"peak_rank":0,"weeks_on_chart":4},{"name":"The Great Divide","artist":"Noah Kahan","image":"https://charts-static.billboard.com/img/2026/05/noah-kahan-h8e-thegreatdivide-uy9-180x180.jpg","rank":6,"last_week_rank":1,"peak_rank":0,"weeks_on_chart":7},{"name":"ARIRANG","artist":"BTS","image":"https://charts-static.billboard.com/img/2026/03/bts-jtk-arirang-z0m-180x180.jpg","rank":7,"last_week_rank":1,"peak_rank":0,"weeks_on_chart":11},{"name":"Dandelion","artist":"Ella Langley","image":"https://charts-static.billboard.com/img/2026/04/ellalangley-0yx-dandelion-1tg-180x180.jpg","rank":8,"last_week_rank":3,"peak_rank":0,"weeks_on_chart":9},{"name":"You'll Be Alright, Kid","artist":"Alex Warren","image":"https://charts-static.billboard.com/img/2024/10/alexwarren-vcb-youllbealrightkid-35e-180x180.jpg","rank":9,"last_week_rank":2,"peak_rank":0,"weeks_on_chart":39},{"name":"KPop Demon Hunters","artist":"Soundtrack","image":"https://charts-static.billboard.com/img/2025/07/soundtrack-000-kpopdemonhunters-tuo-180x180.jpg","rank":10,"last_week_rank":1,"peak_rank":0,"weeks_on_chart":50}]}