{"date":"2026-05-12","data":[{"name":"Nebunatica","artist":"MADATORRICELLI x LiToo The Purp","image":"","rank":1,"last_week_rank":1,"peak_rank":0,"weeks_on_chart":1},{"name":"Treci Peste","artist":"Vanilla","image":"","rank":2,"last_week_rank":1,"peak_rank":0,"weeks_on_chart":11},{"name":"Te Juri Ca Vrei","artist":"Mariano","image":"","rank":3,"last_week_rank":2,"peak_rank":0,"weeks_on_chart":9},{"name":"Ma Suna Nebunele","artist":"Lazy Ed","image":"","rank":4,"last_week_rank":3,"peak_rank":0,"weeks_on_chart":11},{"name":"Mor Dupa Tine","artist":"Lazy Ed X Jo","image":"https://www.billboard.com/wp-content/themes/vip/pmc-billboard-2021/assets/public/lazyload-fallback.gif","rank":5,"last_week_rank":1,"peak_rank":0,"weeks_on_chart":5},{"name":"Papaya","artist":"Babasha","image":"https://www.billboard.com/wp-content/themes/vip/pmc-billboard-2021/assets/public/lazyload-fallback.gif","rank":6,"last_week_rank":6,"peak_rank":0,"weeks_on_chart":8},{"name":"Na Belea","artist":"MADATORRICELLI","image":"https://www.billboard.com/wp-content/themes/vip/pmc-billboard-2021/assets/public/lazyload-fallback.gif","rank":7,"last_week_rank":7,"peak_rank":0,"weeks_on_chart":6},{"name":"Izabela","artist":"Connect-R","image":"https://www.billboard.com/wp-content/themes/vip/pmc-billboard-2021/assets/public/lazyload-fallback.gif","rank":8,"last_week_rank":4,"peak_rank":0,"weeks_on_chart":3},{"name":"Gagicuta Body Show","artist":"Tzanca Uraganu","image":"https://www.billboard.com/wp-content/themes/vip/pmc-billboard-2021/assets/public/lazyload-fallback.gif","rank":9,"last_week_rank":3,"peak_rank":0,"weeks_on_chart":7},{"name":"Taj Mahal","artist":"rares, Lazy Ed & Costel Biju","image":"https://www.billboard.com/wp-content/themes/vip/pmc-billboard-2021/assets/public/lazyload-fallback.gif","rank":10,"last_week_rank":2,"peak_rank":0,"weeks_on_chart":8},{"name":"Swim","artist":"BTS","image":"https://charts-static.billboard.com/img/2026/03/bts-jtk-swim-8po-180x180.jpg","rank":11,"last_week_rank":4,"peak_rank":0,"weeks_on_chart":7},{"name":"Billie Jean","artist":"Michael Jackson","image":"https://charts-static.billboard.com/img/2009/07/michael-jackson-y4h-billiejean-u1v-180x180.jpg","rank":12,"last_week_rank":12,"peak_rank":0,"weeks_on_chart":1},{"name":"Cupidoane","artist":"Tzanca Uraganu","image":"https://www.billboard.com/wp-content/themes/vip/pmc-billboard-2021/assets/public/lazyload-fallback.gif","rank":13,"last_week_rank":4,"peak_rank":0,"weeks_on_chart":10},{"name":"Beauty And A Beat","artist":"Justin Bieber Featuring Nicki Minaj","image":"https://charts-static.billboard.com/img/2012/07/justin-bieber-dj8-beautyandabeat-3bw-180x180.jpg","rank":14,"last_week_rank":6,"peak_rank":0,"weeks_on_chart":4},{"name":"Peter Parker (Balkanic Version)","artist":"Lele X Petre Stefan","image":"https://www.billboard.com/wp-content/themes/vip/pmc-billboard-2021/assets/public/lazyload-fallback.gif","rank":15,"last_week_rank":1,"peak_rank":0,"weeks_on_chart":11},{"name":"Dracula","artist":"Tame Impala & JENNIE","image":"https://charts-static.billboard.com/img/2025/10/tame-impala-nyr-dracula-y03-180x180.jpg","rank":16,"last_week_rank":9,"peak_rank":0,"weeks_on_chart":10},{"name":"Talentul Meu Misto","artist":"Luis Gabriel","image":"https://www.billboard.com/wp-content/themes/vip/pmc-billboard-2021/assets/public/lazyload-fallback.gif","rank":17,"last_week_rank":15,"peak_rank":0,"weeks_on_chart":6},{"name":"Jamaican (Bam Bam)","artist":"HUGEL & SOLTO","image":"https://charts-static.billboard.com/img/2025/11/hugel-fga-jamaicanbambam-1yd-180x180.jpg","rank":18,"last_week_rank":17,"peak_rank":0,"weeks_on_chart":5},{"name":"Stiu Ca Ti-e Dor","artist":"Berechet, Vanilla, Cercel & Siiempre","image":"https://www.billboard.com/wp-content/themes/vip/pmc-billboard-2021/assets/public/lazyload-fallback.gif","rank":19,"last_week_rank":6,"peak_rank":0,"weeks_on_chart":16},{"name":"Beat It","artist":"Michael Jackson","image":"https://charts-static.billboard.com/img/2009/07/michael-jackson-y4h-beatit-qy3-180x180.jpg","rank":20,"last_week_rank":20,"peak_rank":0,"weeks_on_chart":1},{"name":"Dirty Diana","artist":"Michael Jackson","image":"https://charts-static.billboard.com/img/2009/07/michael-jackson-y4h-dirtydiana-3do-180x180.jpg","rank":21,"last_week_rank":21,"peak_rank":0,"weeks_on_chart":1},{"name":"Trag In Ea","artist":"MADATORRICELLI","image":"https://www.billboard.com/wp-content/themes/vip/pmc-billboard-2021/assets/public/lazyload-fallback.gif","rank":22,"last_week_rank":7,"peak_rank":0,"weeks_on_chart":9},{"name":"Babydoll","artist":"Dominic Fike","image":"https://charts-static.billboard.com/img/2026/02/dominicfike-0xp-babydoll-xdy-180x180.jpg","rank":23,"last_week_rank":9,"peak_rank":0,"weeks_on_chart":11},{"name":"(When You Gonna) Give It Up To Me","artist":"Sean Paul Featuring Keyshia Cole","image":"https://charts-static.billboard.com/img/2006/07/sean-paul-rss-whenyougonnagiveituptome-k8t-180x180.jpg","rank":24,"last_week_rank":6,"peak_rank":0,"weeks_on_chart":16},{"name":"DEUCESS","artist":"Berechet & Vanilla","image":"https://www.billboard.com/wp-content/themes/vip/pmc-billboard-2021/assets/public/lazyload-fallback.gif","rank":25,"last_week_rank":25,"peak_rank":0,"weeks_on_chart":1}]}