{"date":"2026-07-21","data":[{"name":"Red Bull 64 Bars","artist":"Avi & FAVST","image":"","rank":1,"last_week_rank":1,"peak_rank":0,"weeks_on_chart":1},{"name":"Nareszcie","artist":"Meskie Granie Orkiestra 2026: Igor Herbut, Zalia & Vito Bambino","image":"","rank":2,"last_week_rank":1,"peak_rank":0,"weeks_on_chart":11},{"name":"Mallorca","artist":"Hellfield X Sentino","image":"","rank":3,"last_week_rank":3,"peak_rank":0,"weeks_on_chart":7},{"name":"California Love","artist":"White 2115, VVSimon & Palar","image":"","rank":4,"last_week_rank":2,"peak_rank":0,"weeks_on_chart":16},{"name":"Saudi","artist":"Tax Free, Malik Montana & Kazior Featuring TYK","image":"https://www.billboard.com/wp-content/themes/vip/pmc-billboard-2021/assets/public/lazyload-fallback.gif","rank":5,"last_week_rank":1,"peak_rank":0,"weeks_on_chart":10},{"name":"CZEMPION 2","artist":"Malik Montana X Kizo","image":"https://www.billboard.com/wp-content/themes/vip/pmc-billboard-2021/assets/public/lazyload-fallback.gif","rank":6,"last_week_rank":3,"peak_rank":0,"weeks_on_chart":2},{"name":"tylko kochaj mnie","artist":"Zalia","image":"https://www.billboard.com/wp-content/themes/vip/pmc-billboard-2021/assets/public/lazyload-fallback.gif","rank":7,"last_week_rank":7,"peak_rank":0,"weeks_on_chart":2},{"name":"Lubie Cie Jak Lato","artist":"MODELKI","image":"https://www.billboard.com/wp-content/themes/vip/pmc-billboard-2021/assets/public/lazyload-fallback.gif","rank":8,"last_week_rank":8,"peak_rank":0,"weeks_on_chart":7},{"name":"Latamy","artist":"Tax Free, Malik Montana, Kazior & 730 Huncho","image":"https://www.billboard.com/wp-content/themes/vip/pmc-billboard-2021/assets/public/lazyload-fallback.gif","rank":9,"last_week_rank":8,"peak_rank":0,"weeks_on_chart":3},{"name":"Pach Pach","artist":"Majki & Major SPZ","image":"https://www.billboard.com/wp-content/themes/vip/pmc-billboard-2021/assets/public/lazyload-fallback.gif","rank":10,"last_week_rank":3,"peak_rank":0,"weeks_on_chart":16},{"name":"UUU AAA","artist":"Tax Free, Malik Montana, Kazior, CUZCO$ & Lot808","image":"https://www.billboard.com/wp-content/themes/vip/pmc-billboard-2021/assets/public/lazyload-fallback.gif","rank":11,"last_week_rank":11,"peak_rank":0,"weeks_on_chart":1},{"name":"Stan Deweloperski","artist":"Sequento X Cypis","image":"https://www.billboard.com/wp-content/themes/vip/pmc-billboard-2021/assets/public/lazyload-fallback.gif","rank":12,"last_week_rank":7,"peak_rank":0,"weeks_on_chart":9},{"name":"Napalona","artist":"SxK","image":"https://www.billboard.com/wp-content/themes/vip/pmc-billboard-2021/assets/public/lazyload-fallback.gif","rank":13,"last_week_rank":4,"peak_rank":0,"weeks_on_chart":8},{"name":"Ty Masz","artist":"Gibbs Featuring Kukon","image":"https://www.billboard.com/wp-content/themes/vip/pmc-billboard-2021/assets/public/lazyload-fallback.gif","rank":14,"last_week_rank":4,"peak_rank":0,"weeks_on_chart":11},{"name":"To Cos","artist":"White 2115, Palar & VVSimon","image":"https://www.billboard.com/wp-content/themes/vip/pmc-billboard-2021/assets/public/lazyload-fallback.gif","rank":15,"last_week_rank":11,"peak_rank":0,"weeks_on_chart":9},{"name":"Dai Dai (FIFA World Cup Official Song 2026)","artist":"Shakira X Burna Boy","image":"https://charts-static.billboard.com/img/2026/05/shakira-5cv-daidaififaworldcupofficialsong2026-dao-180x180.jpg","rank":16,"last_week_rank":16,"peak_rank":0,"weeks_on_chart":2},{"name":"Dracula","artist":"Tame Impala & JENNIE","image":"https://charts-static.billboard.com/img/2025/10/tame-impala-nyr-dracula-y03-180x180.jpg","rank":17,"last_week_rank":4,"peak_rank":0,"weeks_on_chart":18},{"name":"Fantazje","artist":"MIU Featuring Pezet & Bedoes 2115","image":"https://www.billboard.com/wp-content/themes/vip/pmc-billboard-2021/assets/public/lazyload-fallback.gif","rank":18,"last_week_rank":1,"peak_rank":0,"weeks_on_chart":16},{"name":"Beauty And A Beat","artist":"Justin Bieber Featuring Nicki Minaj","image":"https://charts-static.billboard.com/img/2012/07/justin-bieber-dj8-beautyandabeat-3bw-180x180.jpg","rank":19,"last_week_rank":5,"peak_rank":0,"weeks_on_chart":13},{"name":"Kalinka","artist":"Majki X Major SPZ","image":"https://www.billboard.com/wp-content/themes/vip/pmc-billboard-2021/assets/public/lazyload-fallback.gif","rank":20,"last_week_rank":6,"peak_rank":0,"weeks_on_chart":31},{"name":"Dopoki Sie Nie Znudzisz","artist":"MIU Featuring Zalia","image":"https://www.billboard.com/wp-content/themes/vip/pmc-billboard-2021/assets/public/lazyload-fallback.gif","rank":21,"last_week_rank":1,"peak_rank":0,"weeks_on_chart":47},{"name":"Zabiore Cie Tam","artist":"Fukaj Featuring Vito Bambino","image":"https://www.billboard.com/wp-content/themes/vip/pmc-billboard-2021/assets/public/lazyload-fallback.gif","rank":22,"last_week_rank":2,"peak_rank":0,"weeks_on_chart":42},{"name":"FACECARD","artist":"Fagata Featuring MODELKI","image":"https://www.billboard.com/wp-content/themes/vip/pmc-billboard-2021/assets/public/lazyload-fallback.gif","rank":23,"last_week_rank":13,"peak_rank":0,"weeks_on_chart":2},{"name":"jeszcze raz?","artist":"OKI Featuring Ewa Farna, Young Igi & Otsochodzi","image":"https://www.billboard.com/wp-content/themes/vip/pmc-billboard-2021/assets/public/lazyload-fallback.gif","rank":24,"last_week_rank":7,"peak_rank":0,"weeks_on_chart":5},{"name":"Kamikaze","artist":"Mata Featuring Skolim & Khaid","image":"https://www.billboard.com/wp-content/themes/vip/pmc-billboard-2021/assets/public/lazyload-fallback.gif","rank":25,"last_week_rank":1,"peak_rank":0,"weeks_on_chart":38}]}