{"date":"2026-04-14","data":[{"name":"Fantazje","artist":"MIU Featuring Pezet & Bedoes 2115","image":"","rank":1,"last_week_rank":1,"peak_rank":0,"weeks_on_chart":3},{"name":"California Love","artist":"White 2115, VVSimon & Palar","image":"","rank":2,"last_week_rank":2,"peak_rank":0,"weeks_on_chart":3},{"name":"Pach Pach","artist":"Majki & Major SPZ","image":"","rank":3,"last_week_rank":3,"peak_rank":0,"weeks_on_chart":3},{"name":"Polska Vixa","artist":"Kizo, MIU & Diiya","image":"","rank":4,"last_week_rank":3,"peak_rank":0,"weeks_on_chart":2},{"name":"my love","artist":"Oki Featuring MGK","image":"https://www.billboard.com/wp-content/themes/vip/pmc-billboard-2021/assets/public/lazyload-fallback.gif","rank":5,"last_week_rank":5,"peak_rank":0,"weeks_on_chart":1},{"name":"Dracula","artist":"Tame Impala & JENNIE","image":"https://charts-static.billboard.com/img/2025/10/tame-impala-nyr-dracula-y03-180x180.jpg","rank":6,"last_week_rank":5,"peak_rank":0,"weeks_on_chart":5},{"name":"Babydoll","artist":"Dominic Fike","image":"https://charts-static.billboard.com/img/2026/02/dominicfike-0xp-babydoll-xdy-180x180.jpg","rank":7,"last_week_rank":4,"peak_rank":0,"weeks_on_chart":7},{"name":"nobodylovesu","artist":"Oki","image":"https://www.billboard.com/wp-content/themes/vip/pmc-billboard-2021/assets/public/lazyload-fallback.gif","rank":8,"last_week_rank":8,"peak_rank":0,"weeks_on_chart":1},{"name":"shoota!!!","artist":"Oki","image":"https://www.billboard.com/wp-content/themes/vip/pmc-billboard-2021/assets/public/lazyload-fallback.gif","rank":9,"last_week_rank":9,"peak_rank":0,"weeks_on_chart":1},{"name":"Wieczor Kawalerski","artist":"White 2115","image":"https://www.billboard.com/wp-content/themes/vip/pmc-billboard-2021/assets/public/lazyload-fallback.gif","rank":10,"last_week_rank":10,"peak_rank":0,"weeks_on_chart":1},{"name":"Ile Bys Dal?","artist":"Oki","image":"https://www.billboard.com/wp-content/themes/vip/pmc-billboard-2021/assets/public/lazyload-fallback.gif","rank":11,"last_week_rank":11,"peak_rank":0,"weeks_on_chart":1},{"name":"Ostatni Raz","artist":"Sentino & BNP Featuring Kaz Balagane","image":"https://www.billboard.com/wp-content/themes/vip/pmc-billboard-2021/assets/public/lazyload-fallback.gif","rank":12,"last_week_rank":1,"peak_rank":0,"weeks_on_chart":5},{"name":"Frisbee","artist":"Sentino & BNP","image":"https://www.billboard.com/wp-content/themes/vip/pmc-billboard-2021/assets/public/lazyload-fallback.gif","rank":13,"last_week_rank":1,"peak_rank":0,"weeks_on_chart":8},{"name":"Dopoki Sie Nie Znudzisz","artist":"MIU Featuring Zalia","image":"https://www.billboard.com/wp-content/themes/vip/pmc-billboard-2021/assets/public/lazyload-fallback.gif","rank":14,"last_week_rank":1,"peak_rank":0,"weeks_on_chart":34},{"name":"Zabiore Cie Tam","artist":"Fukaj Featuring Vito Bambino","image":"https://www.billboard.com/wp-content/themes/vip/pmc-billboard-2021/assets/public/lazyload-fallback.gif","rank":15,"last_week_rank":2,"peak_rank":0,"weeks_on_chart":29},{"name":"Plan B","artist":"Pezet Featuring Mata & Kaz Balagane","image":"https://www.billboard.com/wp-content/themes/vip/pmc-billboard-2021/assets/public/lazyload-fallback.gif","rank":16,"last_week_rank":2,"peak_rank":0,"weeks_on_chart":24},{"name":"Kalinka","artist":"Majki X Major SPZ","image":"https://www.billboard.com/wp-content/themes/vip/pmc-billboard-2021/assets/public/lazyload-fallback.gif","rank":17,"last_week_rank":6,"peak_rank":0,"weeks_on_chart":18},{"name":"da da da (zyje dla rapu)","artist":"spazma","image":"https://www.billboard.com/wp-content/themes/vip/pmc-billboard-2021/assets/public/lazyload-fallback.gif","rank":18,"last_week_rank":18,"peak_rank":0,"weeks_on_chart":2},{"name":"Stateside","artist":"PinkPantheress With Zara Larsson","image":"https://charts-static.billboard.com/img/2026/01/pinkpantheress-j53-stateside-b4j-180x180.jpg","rank":19,"last_week_rank":3,"peak_rank":0,"weeks_on_chart":7},{"name":"After","artist":"Tax Free","image":"https://www.billboard.com/wp-content/themes/vip/pmc-billboard-2021/assets/public/lazyload-fallback.gif","rank":20,"last_week_rank":1,"peak_rank":0,"weeks_on_chart":13},{"name":"End Of Beginning","artist":"Djo","image":"https://charts-static.billboard.com/img/2024/03/djo-fyo-endofbeginning-8q3-180x180.jpg","rank":21,"last_week_rank":6,"peak_rank":0,"weeks_on_chart":20},{"name":"(When You Gonna) Give It Up To Me","artist":"Sean Paul Featuring Keyshia Cole","image":"https://charts-static.billboard.com/img/2006/07/sean-paul-rss-whenyougonnagiveituptome-k8t-180x180.jpg","rank":22,"last_week_rank":22,"peak_rank":0,"weeks_on_chart":5},{"name":"Penthouse 2","artist":"Sentino / Koneser / BNP","image":"https://www.billboard.com/wp-content/themes/vip/pmc-billboard-2021/assets/public/lazyload-fallback.gif","rank":23,"last_week_rank":2,"peak_rank":0,"weeks_on_chart":6},{"name":"Kolejna Noc","artist":"Wac Toja","image":"https://www.billboard.com/wp-content/themes/vip/pmc-billboard-2021/assets/public/lazyload-fallback.gif","rank":24,"last_week_rank":24,"peak_rank":0,"weeks_on_chart":1},{"name":"Where Is My Husband!","artist":"RAYE","image":"https://charts-static.billboard.com/img/2025/10/raye-azb-whereismyhusband-nm1-180x180.jpg","rank":25,"last_week_rank":9,"peak_rank":0,"weeks_on_chart":20}]}