{"date":"2023-04-25","data":[{"name":"Ella Baila Sola","artist":"Eslabon Armado X Peso Pluma","image":"https://charts-static.billboard.com/img/2023/04/eslabon-armado-v4x-ellabailasola-g5q-180x180.jpg","rank":1,"last_week_rank":3,"peak_rank":1,"weeks_on_chart":5},{"name":"Flowers","artist":"Miley Cyrus","image":"https://charts-static.billboard.com/img/2023/01/miley-cyrus-jca-flowers-l87-180x180.jpg","rank":2,"last_week_rank":1,"peak_rank":1,"weeks_on_chart":14},{"name":"La Bebe","artist":"Yng Lvcas x Peso Pluma","image":"https://charts-static.billboard.com/img/2023/02/ynglvcas-xgk-labebe-g0c-180x180.jpg","rank":3,"last_week_rank":4,"peak_rank":3,"weeks_on_chart":8},{"name":"Kill Bill","artist":"SZA","image":"https://charts-static.billboard.com/img/2022/12/sza-mhq-killbill-w9e-180x180.jpg","rank":4,"last_week_rank":7,"peak_rank":1,"weeks_on_chart":19},{"name":"Un x100to","artist":"Grupo Frontera X Bad Bunny","image":"https://charts-static.billboard.com/img/2023/04/grupofrontera-cdi-unx100to-wbq-180x180.jpg","rank":5,"last_week_rank":null,"peak_rank":5,"weeks_on_chart":1},{"name":"Die For You","artist":"The Weeknd & Ariana Grande","image":"https://charts-static.billboard.com/img/2016/12/the-weeknd-xmx-dieforyou-89b-180x180.jpg","rank":6,"last_week_rank":5,"peak_rank":2,"weeks_on_chart":59},{"name":"Calm Down","artist":"Rema & Selena Gomez","image":"https://charts-static.billboard.com/img/2022/04/rema-000-calmdown-55o-180x180.jpg","rank":7,"last_week_rank":6,"peak_rank":3,"weeks_on_chart":42},{"name":"Last Night","artist":"Morgan Wallen","image":"https://charts-static.billboard.com/img/2016/08/morgan-wallen-nlu-180x180.jpg","rank":8,"last_week_rank":8,"peak_rank":5,"weeks_on_chart":12},{"name":"Cupid","artist":"Fifty Fifty","image":"https://charts-static.billboard.com/img/2023/03/fifty-fifty-000-cupid-b0k-180x180.jpg","rank":9,"last_week_rank":13,"peak_rank":9,"weeks_on_chart":6},{"name":"TQG","artist":"Karol G x Shakira","image":"https://charts-static.billboard.com/img/2023/03/karol-g-7vn-tqg-o8m-180x180.jpg","rank":10,"last_week_rank":9,"peak_rank":1,"weeks_on_chart":8},{"name":"Princess Diana","artist":"Ice Spice & Nicki Minaj","image":"https://charts-static.billboard.com/img/2023/04/icespice-ouz-princessdiana-11d-180x180.jpg","rank":11,"last_week_rank":null,"peak_rank":11,"weeks_on_chart":1},{"name":"Daylight","artist":"David Kushner","image":"https://charts-static.billboard.com/img/2023/04/davidkushner-mih-daylight-p6e-180x180.jpg","rank":12,"last_week_rank":null,"peak_rank":12,"weeks_on_chart":1},{"name":"Search & Rescue","artist":"Drake","image":"https://charts-static.billboard.com/img/2023/04/drake-04g-searchrescue-ls2-180x180.jpg","rank":13,"last_week_rank":2,"peak_rank":2,"weeks_on_chart":2},{"name":"Idol","artist":"YOASOBI","image":"https://charts-static.billboard.com/img/2023/04/yoasobi-i3g-idol-h4w-180x180.jpg","rank":14,"last_week_rank":null,"peak_rank":14,"weeks_on_chart":1},{"name":"Boy's A Liar, Pt. 2","artist":"PinkPantheress & Ice Spice","image":"https://charts-static.billboard.com/img/2023/02/pinkpantheress-dxq-boysaliarpt2-t8h-180x180.jpg","rank":15,"last_week_rank":12,"peak_rank":3,"weeks_on_chart":11},{"name":"Chemical","artist":"Post Malone","image":"https://charts-static.billboard.com/img/2023/04/post-malone-8b5-chemical-aqu-180x180.jpg","rank":16,"last_week_rank":null,"peak_rank":16,"weeks_on_chart":1},{"name":"Beso","artist":"Rosalia & Rauw Alejandro","image":"https://charts-static.billboard.com/img/2023/04/rosalia-88x-beso-5h7-180x180.jpg","rank":17,"last_week_rank":16,"peak_rank":10,"weeks_on_chart":4},{"name":"Anti-Hero","artist":"Taylor Swift","image":"https://charts-static.billboard.com/img/2022/11/taylor-swift-824-antihero-5fz-180x180.jpg","rank":18,"last_week_rank":15,"peak_rank":1,"weeks_on_chart":26},{"name":"As It Was","artist":"Harry Styles","image":"https://charts-static.billboard.com/img/2022/04/harry-styles-6jk-asitwas-frn-180x180.jpg","rank":19,"last_week_rank":14,"peak_rank":1,"weeks_on_chart":55},{"name":"Creepin'","artist":"Metro Boomin, The Weeknd & 21 Savage","image":"https://charts-static.billboard.com/img/2013/08/metro-boomin-nxb-180x180.jpg","rank":20,"last_week_rank":17,"peak_rank":3,"weeks_on_chart":20},{"name":"I Am","artist":"IVE","image":"https://charts-static.billboard.com/img/2021/12/ive-bdq-180x180.jpg","rank":21,"last_week_rank":52,"peak_rank":21,"weeks_on_chart":2},{"name":"PRC","artist":"Peso Pluma X Natanael Cano","image":"https://charts-static.billboard.com/img/2023/02/pesopluma-7gg-prc-ejl-180x180.jpg","rank":22,"last_week_rank":23,"peak_rank":22,"weeks_on_chart":12},{"name":"Flower","artist":"Jisoo","image":"https://charts-static.billboard.com/img/2023/04/jisoo-000-flower-qsm-180x180.jpg","rank":23,"last_week_rank":11,"peak_rank":2,"weeks_on_chart":3},{"name":"Por Las Noches","artist":"Peso Pluma","image":"https://charts-static.billboard.com/img/2023/02/pesopluma-7gg-porlasnoches-dbr-180x180.jpg","rank":24,"last_week_rank":28,"peak_rank":24,"weeks_on_chart":8},{"name":"Like Crazy","artist":"Jimin","image":"https://charts-static.billboard.com/img/2016/03/ji-min-7g4-180x180.jpg","rank":25,"last_week_rank":10,"peak_rank":2,"weeks_on_chart":4},{"name":"I'm Good (Blue)","artist":"David Guetta & Bebe Rexha","image":"https://charts-static.billboard.com/img/2022/09/david-guetta-ruw-imgoodblue-rkt-180x180.jpg","rank":26,"last_week_rank":18,"peak_rank":2,"weeks_on_chart":34},{"name":"AMG","artist":"Gabito Ballesteros, Peso Pluma & Natanael Cano","image":"https://charts-static.billboard.com/img/2022/12/gabitoballesteros-000-amg-12z-180x180.jpg","rank":27,"last_week_rank":26,"peak_rank":26,"weeks_on_chart":15},{"name":"Classy 101","artist":"Feid x Young Miko","image":"https://charts-static.billboard.com/img/2023/04/feid-ug7-classy101-uzm-180x180.jpg","rank":28,"last_week_rank":39,"peak_rank":28,"weeks_on_chart":3},{"name":"Unholy","artist":"Sam Smith & Kim Petras","image":"https://charts-static.billboard.com/img/2022/10/sam-smith-jw8-unholy-dry-180x180.jpg","rank":29,"last_week_rank":19,"peak_rank":1,"weeks_on_chart":30},{"name":"Yandel 150","artist":"Yandel & Feid","image":"https://charts-static.billboard.com/img/2023/01/yandel-ugu-yandel150-b2o-180x180.jpg","rank":30,"last_week_rank":20,"peak_rank":13,"weeks_on_chart":15},{"name":"El Azul","artist":"Junior H x Peso Pluma","image":"https://charts-static.billboard.com/img/2023/02/juniorh-og2-elazul-brz-180x180.jpg","rank":31,"last_week_rank":34,"peak_rank":31,"weeks_on_chart":6},{"name":"Until I Found You","artist":"Stephen Sanchez","image":"https://charts-static.billboard.com/img/2022/05/stephensanchez-s9k-untilifoundyou-n64-180x180.jpg","rank":32,"last_week_rank":22,"peak_rank":11,"weeks_on_chart":49},{"name":"Save Your Tears","artist":"The Weeknd & Ariana Grande","image":"https://charts-static.billboard.com/img/2020/12/the-weeknd-xmx-save-your-tears-e5b-180x180.jpg","rank":33,"last_week_rank":27,"peak_rank":1,"weeks_on_chart":120},{"name":"Bzrp Music Sessions, Vol. 53","artist":"Bizarrap & Shakira","image":"https://charts-static.billboard.com/img/2023/01/bizarrap-rsm-bzrpmusicsessionsvol53-gyx-180x180.jpg","rank":34,"last_week_rank":21,"peak_rank":2,"weeks_on_chart":15},{"name":"I Ain't Worried","artist":"OneRepublic","image":"https://charts-static.billboard.com/img/2022/06/onerepublic-m2z-i-aint-worried-6ds-180x180.jpg","rank":35,"last_week_rank":31,"peak_rank":5,"weeks_on_chart":46},{"name":"Fast Car","artist":"Luke Combs","image":"https://charts-static.billboard.com/img/2015/07/luke-combs-9dm-180x180.jpg","rank":36,"last_week_rank":41,"peak_rank":36,"weeks_on_chart":4},{"name":"Golden Hour","artist":"JVKE","image":"https://charts-static.billboard.com/img/2022/09/jvke-4lr-goldenhour-qcn-180x180.jpg","rank":37,"last_week_rank":33,"peak_rank":13,"weeks_on_chart":34},{"name":"Sure Thing","artist":"Miguel","image":"https://charts-static.billboard.com/img/2011/03/miguel-rp9-surething-1an-180x180.jpg","rank":38,"last_week_rank":30,"peak_rank":13,"weeks_on_chart":18},{"name":"Escapism","artist":"RAYE Featuring 070 Shake","image":"https://charts-static.billboard.com/img/2022/12/raye-ufz-escapism-ngt-180x180.jpg","rank":39,"last_week_rank":29,"peak_rank":7,"weeks_on_chart":21},{"name":"Eyes Closed","artist":"Ed Sheeran","image":"https://charts-static.billboard.com/img/2023/04/ed-sheeran-w3r-eyesclosed-u1h-180x180.jpg","rank":40,"last_week_rank":25,"peak_rank":16,"weeks_on_chart":4},{"name":"Heat Waves","artist":"Glass Animals","image":"https://charts-static.billboard.com/img/2020/07/glass-animals-rtd-heat-waves-1lv-180x180.jpg","rank":41,"last_week_rank":58,"peak_rank":1,"weeks_on_chart":120},{"name":"Players","artist":"Coi Leray","image":"https://charts-static.billboard.com/img/2022/12/coileray-000-players-gon-180x180.jpg","rank":42,"last_week_rank":32,"peak_rank":17,"weeks_on_chart":15},{"name":"Another Love","artist":"Tom Odell","image":"https://charts-static.billboard.com/img/2013/01/tom-odell-qwt-180x180.jpg","rank":43,"last_week_rank":35,"peak_rank":14,"weeks_on_chart":103},{"name":"Snooze","artist":"SZA","image":"https://charts-static.billboard.com/img/2014/04/sza-8os-180x180.jpg","rank":44,"last_week_rank":38,"peak_rank":27,"weeks_on_chart":19},{"name":"OMG","artist":"NewJeans","image":"https://charts-static.billboard.com/img/2023/01/newjeans-9dv-omg-kdx-180x180.jpg","rank":45,"last_week_rank":36,"peak_rank":10,"weeks_on_chart":16},{"name":"Ch y La Pizza","artist":"Fuerza Regida X Natanael Cano","image":"https://charts-static.billboard.com/img/2023/01/fuerzaregida-vjz-chylapizza-m3u-180x180.jpg","rank":46,"last_week_rank":42,"peak_rank":39,"weeks_on_chart":11},{"name":"Blinding Lights","artist":"The Weeknd","image":"https://charts-static.billboard.com/img/2019/12/the-weeknd-xmx-blinding-lights-q48-180x180.jpg","rank":47,"last_week_rank":40,"peak_rank":2,"weeks_on_chart":137},{"name":"Peaches","artist":"Jack Black","image":"https://charts-static.billboard.com/img/2023/04/jack-black-000-peaches-2s6-180x180.jpg","rank":48,"last_week_rank":106,"peak_rank":48,"weeks_on_chart":2},{"name":"Miracle","artist":"Calvin Harris & Ellie Goulding","image":"https://charts-static.billboard.com/img/2023/03/calvin-harris-ds5-miracle-swn-180x180.jpg","rank":49,"last_week_rank":54,"peak_rank":49,"weeks_on_chart":6},{"name":"Never Felt So Alone","artist":"Labrinth","image":"https://charts-static.billboard.com/img/2010/06/labrinth-g0i-106x106.jpg","rank":50,"last_week_rank":93,"peak_rank":50,"weeks_on_chart":2},{"name":"Starboy","artist":"The Weeknd Featuring Daft Punk","image":"https://charts-static.billboard.com/img/2016/10/the-weeknd-xmx-starboy-g5m-180x180.jpg","rank":51,"last_week_rank":49,"peak_rank":34,"weeks_on_chart":94},{"name":"People","artist":"Libianca","image":"https://charts-static.billboard.com/img/2022/12/libianca-000-people-m6t-180x180.jpg","rank":52,"last_week_rank":37,"peak_rank":35,"weeks_on_chart":14},{"name":"La Bachata","artist":"Manuel Turizo","image":"https://charts-static.billboard.com/img/2022/06/manuel-turizo-7zu-labachata-1l6-180x180.jpg","rank":53,"last_week_rank":43,"peak_rank":6,"weeks_on_chart":41},{"name":"Favorite Song","artist":"Toosii","image":"https://charts-static.billboard.com/img/2023/03/toosii-1jf-favoritesong-rl3-180x180.jpg","rank":54,"last_week_rank":50,"peak_rank":50,"weeks_on_chart":9},{"name":"Bebe Dame","artist":"Fuerza Regida X Grupo Frontera","image":"https://charts-static.billboard.com/img/2022/12/fuerzaregida-vjz-bebedame-ai9-180x180.jpg","rank":55,"last_week_rank":69,"peak_rank":17,"weeks_on_chart":16},{"name":"Under The Influence","artist":"Chris Brown","image":"https://charts-static.billboard.com/img/2019/10/chris-brown-94g-undertheinfluence-eql-180x180.jpg","rank":56,"last_week_rank":46,"peak_rank":3,"weeks_on_chart":39},{"name":"Mockingbird","artist":"Eminem","image":"https://charts-static.billboard.com/img/2011/01/eminem-6zg-mockingbird-e6r-180x180.jpg","rank":57,"last_week_rank":45,"peak_rank":42,"weeks_on_chart":27},{"name":"Lavender Haze","artist":"Taylor Swift","image":"https://charts-static.billboard.com/img/2022/11/taylor-swift-824-lavenderhaze-itr-180x180.jpg","rank":58,"last_week_rank":44,"peak_rank":2,"weeks_on_chart":26},{"name":"Kitsch","artist":"IVE","image":"https://charts-static.billboard.com/img/2023/04/ive-bdq-kitsch-5mq-180x180.jpg","rank":59,"last_week_rank":76,"peak_rank":59,"weeks_on_chart":3},{"name":"Thinkin' Bout Me","artist":"Morgan Wallen","image":"https://charts-static.billboard.com/img/2016/08/morgan-wallen-nlu-180x180.jpg","rank":60,"last_week_rank":51,"peak_rank":21,"weeks_on_chart":7},{"name":"Slut Me Out","artist":"NLE Choppa","image":"https://charts-static.billboard.com/img/2023/04/nlechoppa-bxs-slutmeout-nax-180x180.jpg","rank":61,"last_week_rank":48,"peak_rank":48,"weeks_on_chart":3},{"name":"Levitating","artist":"Dua Lipa","image":"https://charts-static.billboard.com/img/2020/04/dua-lipa-eqf-levitating-tr9-180x180.jpg","rank":62,"last_week_rank":55,"peak_rank":2,"weeks_on_chart":133},{"name":"You Proof","artist":"Morgan Wallen","image":"https://charts-static.billboard.com/img/2022/05/morgan-wallen-nlu-you-proof-503-180x180.jpg","rank":63,"last_week_rank":53,"peak_rank":22,"weeks_on_chart":49},{"name":"Perfect","artist":"Ed Sheeran","image":"https://charts-static.billboard.com/img/2011/07/ed-sheeran-w3r-180x180.jpg","rank":64,"last_week_rank":60,"peak_rank":30,"weeks_on_chart":137},{"name":"El Gordo Trae El Mando","artist":"Chino Pacas","image":"https://charts-static.billboard.com/img/2023/02/chinopacas-000-elgordotraeelmando-byk-180x180.jpg","rank":65,"last_week_rank":70,"peak_rank":65,"weeks_on_chart":10},{"name":"Coco Chanel","artist":"Eladio Carrion & Bad Bunny","image":"https://charts-static.billboard.com/img/2020/02/eladiocarrion-6jf-180x180.jpg","rank":66,"last_week_rank":47,"peak_rank":22,"weeks_on_chart":5},{"name":"Me Porto Bonito","artist":"Bad Bunny & Chencho Corleone","image":"https://charts-static.billboard.com/img/2016/10/bad-bunny-c3m-180x180.jpg","rank":67,"last_week_rank":67,"peak_rank":2,"weeks_on_chart":50},{"name":"Stay","artist":"The Kid LAROI & Justin Bieber","image":"https://charts-static.billboard.com/img/2021/07/the-kid-laroi-qev-stay-vsd-180x180.jpg","rank":68,"last_week_rank":56,"peak_rank":1,"weeks_on_chart":93},{"name":"Que Vuelvas","artist":"Carin Leon X Grupo Frontera","image":"https://charts-static.billboard.com/img/2022/12/carinleon-yy4-quevuelvas-4u1-180x180.jpg","rank":69,"last_week_rank":82,"peak_rank":34,"weeks_on_chart":17},{"name":"Someone You Loved","artist":"Lewis Capaldi","image":"https://charts-static.billboard.com/img/2019/02/lewis-capaldi-s0e-someoneyouloved-00a-180x180.jpg","rank":70,"last_week_rank":63,"peak_rank":24,"weeks_on_chart":137},{"name":"Shivers","artist":"Ed Sheeran","image":"https://charts-static.billboard.com/img/2021/09/ed-sheeran-w3r-shivers-9kr-180x180.jpg","rank":71,"last_week_rank":62,"peak_rank":3,"weeks_on_chart":84},{"name":"Hey Mor","artist":"Ozuna Featuring Feid","image":"https://charts-static.billboard.com/img/2016/04/ozuna-gin-180x180.jpg","rank":72,"last_week_rank":57,"peak_rank":27,"weeks_on_chart":27},{"name":"Cold Heart (PNAU Remix)","artist":"Elton John & Dua Lipa","image":"https://charts-static.billboard.com/img/2021/08/elton-john-m6x-cold-heart-pnau-remix-8pz-180x180.jpg","rank":73,"last_week_rank":65,"peak_rank":3,"weeks_on_chart":88},{"name":"Something In The Orange","artist":"Zach Bryan","image":"https://charts-static.billboard.com/img/2022/05/zach-bryan-cfd-something-in-the-orange-8ma-180x180.jpg","rank":74,"last_week_rank":61,"peak_rank":23,"weeks_on_chart":51},{"name":"Here With Me","artist":"d4vd","image":"https://charts-static.billboard.com/img/2022/11/d4vd-7p1-herewithme-8bw-180x180.jpg","rank":75,"last_week_rank":72,"peak_rank":34,"weeks_on_chart":23},{"name":"Titi Me Pregunto","artist":"Bad Bunny","image":"https://charts-static.billboard.com/img/2016/10/bad-bunny-c3m-180x180.jpg","rank":76,"last_week_rank":87,"peak_rank":4,"weeks_on_chart":50},{"name":"Bzrp Music Sessions, Vol. 52","artist":"Bizarrap & Quevedo","image":"https://charts-static.billboard.com/img/2022/07/bizarrap-rsm-bzrp-music-sessions-vol-52-6r7-180x180.jpg","rank":77,"last_week_rank":74,"peak_rank":1,"weeks_on_chart":41},{"name":"Cuff It","artist":"Beyonce","image":"https://charts-static.billboard.com/img/2022/08/beyonce-0na-cuffit-5y5-180x180.jpg","rank":78,"last_week_rank":71,"peak_rank":12,"weeks_on_chart":38},{"name":"See You Again","artist":"Tyler, The Creator Featuring Kali Uchis","image":"https://charts-static.billboard.com/img/2011/05/tyler-the-creator-556-180x180.jpg","rank":79,"last_week_rank":null,"peak_rank":79,"weeks_on_chart":1},{"name":"Ceilings","artist":"Lizzy McAlpine","image":"https://charts-static.billboard.com/img/2023/02/lizzymcalpine-mgv-ceilings-te3-180x180.jpg","rank":80,"last_week_rank":64,"peak_rank":29,"weeks_on_chart":9},{"name":"Made You Look","artist":"Meghan Trainor","image":"https://charts-static.billboard.com/img/2022/11/meghan-trainor-3k0-madeyoulook-3d8-180x180.jpg","rank":81,"last_week_rank":68,"peak_rank":6,"weeks_on_chart":26},{"name":"Sweater Weather","artist":"The Neighbourhood","image":"https://charts-static.billboard.com/img/2013/03/the-neighbourhood-slc-sweaterweather-ft8-180x180.jpg","rank":82,"last_week_rank":83,"peak_rank":25,"weeks_on_chart":134},{"name":"Superhero (Heroes & Villains)","artist":"Metro Boomin, Future & Chris Brown","image":"https://charts-static.billboard.com/img/2013/08/metro-boomin-nxb-180x180.jpg","rank":83,"last_week_rank":84,"peak_rank":8,"weeks_on_chart":20},{"name":"Shorty Party","artist":"Cartel de Santa Featuring La Kelly","image":"https://charts-static.billboard.com/img/2023/03/cartel-de-santa-000-shortyparty-ux7-180x180.jpg","rank":84,"last_week_rank":73,"peak_rank":25,"weeks_on_chart":7},{"name":"Chanel","artist":"Becky G & Peso Pluma","image":"https://charts-static.billboard.com/img/2023/04/becky-g-gw8-chanel-wpi-180x180.jpg","rank":85,"last_week_rank":141,"peak_rank":85,"weeks_on_chart":2},{"name":"La Jumpa","artist":"Arcangel & Bad Bunny","image":"https://charts-static.billboard.com/img/2022/12/arcangel-pqf-lajumpa-vaz-180x180.jpg","rank":86,"last_week_rank":80,"peak_rank":14,"weeks_on_chart":20},{"name":"Ditto","artist":"NewJeans","image":"https://charts-static.billboard.com/img/2022/12/newjeans-9dv-ditto-2fy-180x180.jpg","rank":87,"last_week_rank":66,"peak_rank":8,"weeks_on_chart":18},{"name":"Bones","artist":"Imagine Dragons","image":"https://charts-static.billboard.com/img/2022/03/imagine-dragons-ud7-bones-8cg-180x180.jpg","rank":88,"last_week_rank":77,"peak_rank":32,"weeks_on_chart":58},{"name":"Fin de Semana","artist":"Junior H X Oscar Maydon","image":"https://charts-static.billboard.com/img/2023/01/juniorh-og2-findesemana-0hl-180x180.jpg","rank":89,"last_week_rank":79,"peak_rank":58,"weeks_on_chart":14},{"name":"Just Wanna Rock","artist":"Lil Uzi Vert","image":"https://charts-static.billboard.com/img/2022/10/lil-uzi-vert-g7z-justwannarock-cn5-180x180.jpg","rank":90,"last_week_rank":75,"peak_rank":26,"weeks_on_chart":27},{"name":"Cruel Summer","artist":"Taylor Swift","image":"https://charts-static.billboard.com/img/2006/07/taylor-swift-824-180x180.jpg","rank":91,"last_week_rank":108,"peak_rank":91,"weeks_on_chart":5},{"name":"10:35","artist":"Tiesto Featuring Tate McRae","image":"https://charts-static.billboard.com/img/2022/11/tiesto-e64-1035-tlm-180x180.jpg","rank":92,"last_week_rank":86,"peak_rank":38,"weeks_on_chart":21},{"name":"All Of The Girls You Loved Before","artist":"Taylor Swift","image":"https://charts-static.billboard.com/img/2006/07/taylor-swift-824-180x180.jpg","rank":93,"last_week_rank":59,"peak_rank":10,"weeks_on_chart":5},{"name":"Blank Space","artist":"Taylor Swift","image":"https://charts-static.billboard.com/img/2014/11/taylor-swift-824-blankspace-vgi-180x180.jpg","rank":94,"last_week_rank":97,"peak_rank":94,"weeks_on_chart":36},{"name":"Rich Flex","artist":"Drake & 21 Savage","image":"https://charts-static.billboard.com/img/2009/04/drake-04g-180x180.jpg","rank":95,"last_week_rank":78,"peak_rank":1,"weeks_on_chart":24},{"name":"Trance","artist":"Metro Boomin, Travis Scott & Young Thug","image":"https://charts-static.billboard.com/img/2013/08/metro-boomin-nxb-180x180.jpg","rank":96,"last_week_rank":101,"peak_rank":42,"weeks_on_chart":10},{"name":"Mientras Me Curo del Cora","artist":"Karol G","image":"https://charts-static.billboard.com/img/2016/05/karol-g-7vn-180x180.jpg","rank":97,"last_week_rank":91,"peak_rank":40,"weeks_on_chart":8},{"name":"Believer","artist":"Imagine Dragons","image":"https://charts-static.billboard.com/img/2017/02/imagine-dragons-ud7-believer-hmi-180x180.jpg","rank":98,"last_week_rank":94,"peak_rank":52,"weeks_on_chart":137},{"name":"Bad Habits","artist":"Ed Sheeran","image":"https://charts-static.billboard.com/img/2021/07/ed-sheeran-w3r-bad-habits-i7l-180x180.jpg","rank":99,"last_week_rank":89,"peak_rank":1,"weeks_on_chart":95},{"name":"I Wanna Be Yours","artist":"Arctic Monkeys","image":"https://charts-static.billboard.com/img/2005/11/arctic-monkeys-4ey-180x180.jpg","rank":100,"last_week_rank":100,"peak_rank":71,"weeks_on_chart":33},{"name":"Rock And A Hard Place","artist":"Bailey Zimmerman","image":"https://charts-static.billboard.com/img/2022/06/baileyzimmerman-qt3-rockandahardplace-zsw-180x180.jpg","rank":101,"last_week_rank":85,"peak_rank":59,"weeks_on_chart":43},{"name":"Baby Don't Hurt Me","artist":"David Guetta, Anne-Marie & Coi Leray","image":"https://charts-static.billboard.com/img/2023/04/david-guetta-ruw-babydonthurtme-05a-180x180.jpg","rank":102,"last_week_rank":114,"peak_rank":102,"weeks_on_chart":2},{"name":"Rara Vez","artist":"Milo j","image":"https://charts-static.billboard.com/img/2023/02/miloj-000-raravez-h7n-180x180.jpg","rank":103,"last_week_rank":98,"peak_rank":98,"weeks_on_chart":6},{"name":"Bad Habit","artist":"Steve Lacy","image":"https://charts-static.billboard.com/img/2022/07/steve-lacy-d2o-badhabit-9nj-180x180.jpg","rank":104,"last_week_rank":90,"peak_rank":8,"weeks_on_chart":41},{"name":"Unstoppable","artist":"Sia","image":"https://charts-static.billboard.com/img/2016/02/sia-0sp-unstoppable-08h-180x180.jpg","rank":105,"last_week_rank":95,"peak_rank":79,"weeks_on_chart":62},{"name":"Ojitos Lindos","artist":"Bad Bunny & Bomba Estereo","image":"https://charts-static.billboard.com/img/2016/10/bad-bunny-c3m-180x180.jpg","rank":106,"last_week_rank":102,"peak_rank":4,"weeks_on_chart":50},{"name":"Un Finde   Crossover #2","artist":"Ke personajes X Big One X FMK","image":"https://charts-static.billboard.com/img/2023/04/kepersonajes-000-unfindebigonecrossover2-rmb-180x180.jpg","rank":107,"last_week_rank":183,"peak_rank":107,"weeks_on_chart":2},{"name":"M.A (Mejores Amigos)","artist":"BM","image":"https://charts-static.billboard.com/img/2023/03/bm-000-mamejoresamigos-e7l-180x180.jpg","rank":108,"last_week_rank":81,"peak_rank":81,"weeks_on_chart":2},{"name":"Sunflower (Spider-Man: Into The Spider-Verse)","artist":"Post Malone & Swae Lee","image":"https://charts-static.billboard.com/img/2018/10/post-malone-8b5-sunflowerspidermanintothespiderverse-u2l-180x180.jpg","rank":109,"last_week_rank":111,"peak_rank":41,"weeks_on_chart":137},{"name":"Riptide","artist":"Vance Joy","image":"https://charts-static.billboard.com/img/2014/06/vance-joy-578-riptide-jg9-180x180.jpg","rank":110,"last_week_rank":107,"peak_rank":100,"weeks_on_chart":84},{"name":"Viva La Vida","artist":"Coldplay","image":"https://charts-static.billboard.com/img/2008/05/coldplay-bm3-viva-la-vida-oj6-180x180.jpg","rank":111,"last_week_rank":105,"peak_rank":104,"weeks_on_chart":35},{"name":"Snap","artist":"Rosa Linn","image":"https://charts-static.billboard.com/img/2022/07/rosalinn-rc0-snap-c77-180x180.jpg","rank":112,"last_week_rank":99,"peak_rank":18,"weeks_on_chart":41},{"name":"Feliz Cumpleanos Ferxxo","artist":"Feid","image":"https://charts-static.billboard.com/img/2022/09/feid-ug7-felizcumpleanosferxxo-6cu-180x180.jpg","rank":113,"last_week_rank":92,"peak_rank":61,"weeks_on_chart":33},{"name":"Shape Of You","artist":"Ed Sheeran","image":"https://charts-static.billboard.com/img/2017/01/ed-sheeran-w3r-shape-of-you-0ej-180x180.jpg","rank":114,"last_week_rank":104,"peak_rank":55,"weeks_on_chart":137},{"name":"Cupido","artist":"TINI","image":"https://charts-static.billboard.com/img/2023/03/tini-000-cupido-qco-180x180.jpg","rank":115,"last_week_rank":96,"peak_rank":69,"weeks_on_chart":9},{"name":"One Thing At A Time","artist":"Morgan Wallen","image":"https://charts-static.billboard.com/img/2022/12/morgan-wallen-nlu-onethingatatime-7ay-180x180.jpg","rank":116,"last_week_rank":103,"peak_rank":24,"weeks_on_chart":9},{"name":"Summertime Sadness","artist":"Lana Del Rey vs. Cedric Gervais","image":"https://charts-static.billboard.com/img/2013/06/lana-del-rey-45t-summertimesadness-4lc-180x180.jpg","rank":117,"last_week_rank":118,"peak_rank":89,"weeks_on_chart":37},{"name":"No Role Modelz","artist":"J. Cole","image":"https://charts-static.billboard.com/img/2009/12/j-cole-9on-180x180.jpg","rank":118,"last_week_rank":123,"peak_rank":97,"weeks_on_chart":93},{"name":"Wish You The Best","artist":"Lewis Capaldi","image":"https://charts-static.billboard.com/img/2023/04/lewis-capaldi-s0e-wishyouthebest-8u3-180x180.jpg","rank":119,"last_week_rank":null,"peak_rank":119,"weeks_on_chart":1},{"name":"Yellow","artist":"Coldplay","image":"https://charts-static.billboard.com/img/2005/06/coldplay-bm3-yellow-ty6-180x180.jpg","rank":120,"last_week_rank":120,"peak_rank":68,"weeks_on_chart":106},{"name":"Lovely","artist":"Billie Eilish & Khalid","image":"https://charts-static.billboard.com/img/2018/05/billie-eilish-lrt-lovely-hww-180x180.jpg","rank":121,"last_week_rank":128,"peak_rank":70,"weeks_on_chart":137},{"name":"Take On Me","artist":"a-ha","image":"https://charts-static.billboard.com/img/2013/10/a-ha-zrv-takeonme-c5b-180x180.jpg","rank":122,"last_week_rank":125,"peak_rank":122,"weeks_on_chart":77},{"name":"Igualito A Mi Apa","artist":"Fuerza Regida & Peso Pluma","image":"https://charts-static.billboard.com/img/2018/06/fuerzaregida-vjz-180x180.jpg","rank":123,"last_week_rank":null,"peak_rank":123,"weeks_on_chart":1},{"name":"Take Me To Church","artist":"Hozier","image":"https://charts-static.billboard.com/img/2014/05/hozier-yyf-takemetochurch-5cv-180x180.jpg","rank":124,"last_week_rank":132,"peak_rank":115,"weeks_on_chart":108},{"name":"Fragil","artist":"Yahritza y Su Esencia x Grupo Frontera","image":"https://charts-static.billboard.com/img/2023/04/yahritzaysuesencia-thu-fragil-otx-180x180.jpg","rank":125,"last_week_rank":null,"peak_rank":125,"weeks_on_chart":1},{"name":"Counting Stars","artist":"OneRepublic","image":"https://charts-static.billboard.com/img/2007/04/onerepublic-m2z-180x180.jpg","rank":126,"last_week_rank":133,"peak_rank":96,"weeks_on_chart":108},{"name":"El Tsurito","artist":"Junior H x Gabito Ballesteros x Peso Pluma","image":"https://charts-static.billboard.com/img/2023/04/juniorh-og2-eltsurito-4zq-180x180.jpg","rank":127,"last_week_rank":null,"peak_rank":127,"weeks_on_chart":1},{"name":"Shake It Off","artist":"Taylor Swift","image":"https://charts-static.billboard.com/img/2014/09/taylor-swift-824-shakeitoff-he9-180x180.jpg","rank":128,"last_week_rank":127,"peak_rank":127,"weeks_on_chart":5},{"name":"Chorrito Pa Las Animas","artist":"Feid","image":"https://charts-static.billboard.com/img/2016/10/feid-ug7-180x180.jpg","rank":129,"last_week_rank":110,"peak_rank":82,"weeks_on_chart":15},{"name":"X Si Volvemos","artist":"Karol G x Romeo Santos","image":"https://charts-static.billboard.com/img/2023/02/karol-g-7vn-xsivolvemos-x6a-180x180.jpg","rank":130,"last_week_rank":116,"peak_rank":18,"weeks_on_chart":11},{"name":"Provenza","artist":"Karol G","image":"https://charts-static.billboard.com/img/2022/04/karol-g-7vn-provenza-wah-180x180.jpg","rank":131,"last_week_rank":115,"peak_rank":6,"weeks_on_chart":52},{"name":"Shallow","artist":"Lady Gaga & Bradley Cooper","image":"https://charts-static.billboard.com/img/2008/04/lady-gaga-b8x-180x180.jpg","rank":132,"last_week_rank":122,"peak_rank":59,"weeks_on_chart":134},{"name":"Sunroof","artist":"Nicky Youre & dazy","image":"https://charts-static.billboard.com/img/2022/04/nicky-youre-alv-sunroof-n0r-180x180.jpg","rank":133,"last_week_rank":117,"peak_rank":26,"weeks_on_chart":48},{"name":"Easy On Me","artist":"Adele","image":"https://charts-static.billboard.com/img/2021/10/adele-000-easy-on-me-03x-180x180.jpg","rank":134,"last_week_rank":119,"peak_rank":1,"weeks_on_chart":80},{"name":"Everybody Wants To Rule The World","artist":"Tears For Fears","image":"https://charts-static.billboard.com/img/2014/10/tears-for-fears-19d-everybody-wants-to-rule-the-world-v61-180x180.jpg","rank":135,"last_week_rank":134,"peak_rank":108,"weeks_on_chart":38},{"name":"Moonlight","artist":"Kali Uchis","image":"https://charts-static.billboard.com/img/2023/04/kali-uchis-dp2-moonlight-gol-180x180.jpg","rank":136,"last_week_rank":180,"peak_rank":136,"weeks_on_chart":5},{"name":"Despecha","artist":"Rosalia","image":"https://charts-static.billboard.com/img/2022/08/rosalia-88x-despecha-hsd-180x180.jpg","rank":137,"last_week_rank":124,"peak_rank":6,"weeks_on_chart":38},{"name":"Wasted On You","artist":"Morgan Wallen","image":"https://charts-static.billboard.com/img/2021/01/morgan-wallen-nlu-wasted-on-you-jwj-180x180.jpg","rank":138,"last_week_rank":135,"peak_rank":19,"weeks_on_chart":60},{"name":"Without Me","artist":"Eminem","image":"https://charts-static.billboard.com/img/2013/07/eminem-1xq-180x180.jpg","rank":139,"last_week_rank":144,"peak_rank":39,"weeks_on_chart":80},{"name":"Kizuna No Kiseki","artist":"MAN WITH A MISSION x milet","image":"https://charts-static.billboard.com/img/2023/04/man-with-a-mission-538-kizunanokiseki-f89-180x180.jpg","rank":140,"last_week_rank":null,"peak_rank":140,"weeks_on_chart":1},{"name":"Thought You Should Know","artist":"Morgan Wallen","image":"https://charts-static.billboard.com/img/2022/05/morgan-wallen-nlu-thought-you-should-know-5g7-180x180.jpg","rank":141,"last_week_rank":109,"peak_rank":32,"weeks_on_chart":16},{"name":"Love You Anyway","artist":"Luke Combs","image":"https://charts-static.billboard.com/img/2023/02/luke-combs-9dm-loveyouanyway-08v-180x180.jpg","rank":142,"last_week_rank":121,"peak_rank":31,"weeks_on_chart":9},{"name":"Circles","artist":"Post Malone","image":"https://charts-static.billboard.com/img/2019/09/post-malone-8b5-circles-onc-180x180.jpg","rank":143,"last_week_rank":173,"peak_rank":49,"weeks_on_chart":133},{"name":"Jimmy Cooks","artist":"Drake Featuring 21 Savage","image":"https://charts-static.billboard.com/img/2009/04/drake-04g-180x180.jpg","rank":144,"last_week_rank":137,"peak_rank":3,"weeks_on_chart":44},{"name":"Watermelon Sugar","artist":"Harry Styles","image":"https://charts-static.billboard.com/img/2019/11/harry-styles-6jk-watermelonsugar-w6n-180x180.jpg","rank":145,"last_week_rank":136,"peak_rank":9,"weeks_on_chart":133},{"name":"El Merengue","artist":"Marshmello & Manuel Turizo","image":"https://charts-static.billboard.com/img/2023/03/marshmello-dhc-elmerengue-2ob-180x180.jpg","rank":146,"last_week_rank":139,"peak_rank":103,"weeks_on_chart":6},{"name":"Nonsense","artist":"Sabrina Carpenter","image":"https://charts-static.billboard.com/img/2014/06/sabrina-carpenter-7zv-180x180.jpg","rank":147,"last_week_rank":131,"peak_rank":36,"weeks_on_chart":14},{"name":"Shut Up My Moms Calling","artist":"Hotel Ugly","image":"https://charts-static.billboard.com/img/2022/12/hotelugly-hhr-shutupmymomscalling-xu0-180x180.jpg","rank":148,"last_week_rank":153,"peak_rank":64,"weeks_on_chart":20},{"name":"Style","artist":"Taylor Swift","image":"https://charts-static.billboard.com/img/2006/07/taylor-swift-824-180x180.jpg","rank":149,"last_week_rank":156,"peak_rank":149,"weeks_on_chart":5},{"name":"Dreams","artist":"Fleetwood Mac","image":"https://charts-static.billboard.com/img/2011/05/fleetwood-mac-fe3-dreams-jvb-180x180.jpg","rank":150,"last_week_rank":149,"peak_rank":10,"weeks_on_chart":111},{"name":"Cardigan","artist":"Taylor Swift","image":"https://charts-static.billboard.com/img/2020/08/taylor-swift-824-cardigan-l12-180x180.jpg","rank":151,"last_week_rank":151,"peak_rank":77,"weeks_on_chart":11},{"name":"Set Fire To The Rain","artist":"Adele","image":"https://charts-static.billboard.com/img/2011/03/adele-0zg-setfiretotherain-38o-180x180.jpg","rank":152,"last_week_rank":157,"peak_rank":64,"weeks_on_chart":17},{"name":"Reminder","artist":"The Weeknd","image":"https://charts-static.billboard.com/img/2011/11/the-weeknd-xmx-180x180.jpg","rank":153,"last_week_rank":138,"peak_rank":109,"weeks_on_chart":8},{"name":"No Se Va","artist":"Grupo Frontera","image":"https://charts-static.billboard.com/img/2022/09/grupofrontera-cdi-noseva-92t-180x180.jpg","rank":154,"last_week_rank":193,"peak_rank":31,"weeks_on_chart":30},{"name":"Mercho","artist":"Lil CaKe & Migrantes Featuring Nico Valdi","image":"https://charts-static.billboard.com/img/2023/02/lilcake-000-mercho-gvb-180x180.jpg","rank":155,"last_week_rank":113,"peak_rank":75,"weeks_on_chart":11},{"name":"Dandelions","artist":"Ruth B.","image":"https://charts-static.billboard.com/img/2015/12/ruth-b-6pm-106x106.jpg","rank":156,"last_week_rank":150,"peak_rank":51,"weeks_on_chart":66},{"name":"Gangsta's Paradise","artist":"Coolio Featuring L.V.","image":"https://charts-static.billboard.com/img/2010/11/coolio-i15-gangstasparadise-nqq-180x180.jpg","rank":157,"last_week_rank":130,"peak_rank":21,"weeks_on_chart":92},{"name":"Normal","artist":"Feid","image":"https://charts-static.billboard.com/img/2022/07/feid-ug7-normal-pn7-180x180.jpg","rank":158,"last_week_rank":145,"peak_rank":75,"weeks_on_chart":26},{"name":"Wait For U","artist":"Future Featuring Drake & Tems","image":"https://charts-static.billboard.com/img/1988/03/future-f8b-180x180.jpg","rank":159,"last_week_rank":147,"peak_rank":2,"weeks_on_chart":51},{"name":"Rush","artist":"Ayra Starr","image":"https://charts-static.billboard.com/img/2022/10/ayrastarr-xm9-rush-dub-180x180.jpg","rank":160,"last_week_rank":158,"peak_rank":115,"weeks_on_chart":13},{"name":"Baby Shark","artist":"Pinkfong","image":"https://charts-static.billboard.com/img/2018/07/pinkfong-2rz-babyshark-t58-180x180.jpg","rank":161,"last_week_rank":129,"peak_rank":38,"weeks_on_chart":136},{"name":"Can't Hold Us","artist":"Macklemore & Ryan Lewis Featuring Ray Dalton","image":"https://charts-static.billboard.com/img/2013/02/macklemore-ryan-lewis-79t-cantholdus-lfz-180x180.jpg","rank":162,"last_week_rank":177,"peak_rank":135,"weeks_on_chart":23},{"name":"Too Many Nights","artist":"Metro Boomin Featuring Don Toliver & Future","image":"https://charts-static.billboard.com/img/2013/08/metro-boomin-nxb-180x180.jpg","rank":163,"last_week_rank":null,"peak_rank":23,"weeks_on_chart":10},{"name":"Ghost","artist":"Justin Bieber","image":"https://charts-static.billboard.com/img/2009/07/justin-bieber-f8k-180x180.jpg","rank":164,"last_week_rank":146,"peak_rank":16,"weeks_on_chart":78},{"name":"Efecto","artist":"Bad Bunny","image":"https://charts-static.billboard.com/img/2016/10/bad-bunny-c3m-180x180.jpg","rank":165,"last_week_rank":154,"peak_rank":7,"weeks_on_chart":50},{"name":"Pink + White","artist":"Frank Ocean","image":"https://charts-static.billboard.com/img/2011/05/frank-ocean-3ku-180x180.jpg","rank":166,"last_week_rank":null,"peak_rank":166,"weeks_on_chart":1},{"name":"Sweet Child O' Mine","artist":"Guns N' Roses","image":"https://charts-static.billboard.com/img/2010/07/guns-n-roses-tp2-sweet-child-o-mine-jcn-180x180.jpg","rank":167,"last_week_rank":167,"peak_rank":57,"weeks_on_chart":101},{"name":"Nosso Quadro","artist":"Ana Castela","image":"https://charts-static.billboard.com/img/2023/02/anacastela-000-nossoquadro-uy8-180x180.jpg","rank":168,"last_week_rank":148,"peak_rank":95,"weeks_on_chart":8},{"name":"Low Down","artist":"Lil Baby","image":"https://charts-static.billboard.com/img/2017/11/lilbaby-kyx-180x180.jpg","rank":169,"last_week_rank":160,"peak_rank":130,"weeks_on_chart":4},{"name":"When I Was Your Man","artist":"Bruno Mars","image":"https://charts-static.billboard.com/img/2012/12/bruno-mars-c75-wheniwasyourman-k6t-180x180.jpg","rank":170,"last_week_rank":166,"peak_rank":74,"weeks_on_chart":30},{"name":"We Found Love","artist":"Rihanna Featuring Calvin Harris","image":"https://charts-static.billboard.com/img/2011/10/rihanna-k0p-wefoundlove-gf6-180x180.jpg","rank":171,"last_week_rank":170,"peak_rank":47,"weeks_on_chart":10},{"name":"I Know","artist":"Kanii","image":"https://charts-static.billboard.com/img/2023/04/kanii-s2p-iknow-phw-180x180.jpg","rank":172,"last_week_rank":112,"peak_rank":112,"weeks_on_chart":3},{"name":"Lover","artist":"Taylor Swift","image":"https://charts-static.billboard.com/img/2019/08/taylor-swift-824-lover-b71-180x180.jpg","rank":173,"last_week_rank":181,"peak_rank":173,"weeks_on_chart":4},{"name":"People Pt.2","artist":"Agust D & IU","image":"https://charts-static.billboard.com/img/2023/04/agustd-000-peoplept2-lqr-180x180.jpg","rank":174,"last_week_rank":24,"peak_rank":24,"weeks_on_chart":2},{"name":"Don't Blame Me","artist":"Taylor Swift","image":"https://charts-static.billboard.com/img/2006/07/taylor-swift-824-180x180.jpg","rank":175,"last_week_rank":188,"peak_rank":124,"weeks_on_chart":14},{"name":"Every Breath You Take","artist":"The Police","image":"https://charts-static.billboard.com/img/2011/02/the-police-yp0-every-breath-you-take-4oi-180x180.jpg","rank":176,"last_week_rank":161,"peak_rank":107,"weeks_on_chart":41},{"name":"Enemy","artist":"Imagine Dragons X JID","image":"https://charts-static.billboard.com/img/2021/11/imagine-dragons-ud7-enemy-hcl-180x180.jpg","rank":177,"last_week_rank":159,"peak_rank":3,"weeks_on_chart":77},{"name":"Miss You","artist":"Oliver Tree & Robin Schulz","image":"https://charts-static.billboard.com/img/2022/10/oliver-tree-8zt-missyou-xhc-180x180.jpg","rank":178,"last_week_rank":152,"peak_rank":11,"weeks_on_chart":28},{"name":"Numb","artist":"Linkin Park","image":"https://charts-static.billboard.com/img/2006/09/linkin-park-hil-numb-kz6-180x180.jpg","rank":179,"last_week_rank":182,"peak_rank":166,"weeks_on_chart":4},{"name":"Shut Down","artist":"BLACKPINK","image":"https://charts-static.billboard.com/img/2016/08/blackpink-l5z-180x180.jpg","rank":180,"last_week_rank":189,"peak_rank":1,"weeks_on_chart":27},{"name":"Trustfall","artist":"P!nk","image":"https://charts-static.billboard.com/img/2023/02/pnk-it7-trustfall-0i5-180x180.jpg","rank":181,"last_week_rank":171,"peak_rank":70,"weeks_on_chart":12},{"name":"Happier Than Ever","artist":"Billie Eilish","image":"https://charts-static.billboard.com/img/2021/08/billie-eilish-lrt-happier-than-ever-xd9-180x180.jpg","rank":182,"last_week_rank":162,"peak_rank":6,"weeks_on_chart":87},{"name":"Smells Like Teen Spirit","artist":"Nirvana","image":"https://charts-static.billboard.com/img/2011/04/nirvana-ug8-smells-like-teen-spirit-is8-180x180.jpg","rank":183,"last_week_rank":174,"peak_rank":92,"weeks_on_chart":111},{"name":"Money Trees","artist":"Kendrick Lamar Featuring Jay Rock","image":"https://charts-static.billboard.com/img/2010/10/kendrick-lamar-atc-180x180.jpg","rank":184,"last_week_rank":196,"peak_rank":184,"weeks_on_chart":3},{"name":"The Kind Of Love We Make","artist":"Luke Combs","image":"https://charts-static.billboard.com/img/2022/07/luke-combs-9dm-the-kind-of-love-we-make-hod-180x180.jpg","rank":185,"last_week_rank":172,"peak_rank":38,"weeks_on_chart":40},{"name":"Hotel California","artist":"Eagles","image":"https://charts-static.billboard.com/img/2016/02/eagles-ma9-hotelcalifornia-f0i-180x180.jpg","rank":186,"last_week_rank":168,"peak_rank":132,"weeks_on_chart":105},{"name":"Wake Me Up!","artist":"Avicii","image":"https://charts-static.billboard.com/img/2013/07/avicii-anu-wakemeup-r5c-180x180.jpg","rank":187,"last_week_rank":191,"peak_rank":154,"weeks_on_chart":39},{"name":"Bohemian Rhapsody","artist":"Queen","image":"https://charts-static.billboard.com/img/2005/02/queen-az3-bohemianrhapsody-8fx-180x180.jpg","rank":188,"last_week_rank":null,"peak_rank":97,"weeks_on_chart":115},{"name":"Don't Stop Believin'","artist":"Journey","image":"https://charts-static.billboard.com/img/2005/08/journey-0b3-dontstopbelievin-mvt-180x180.jpg","rank":189,"last_week_rank":169,"peak_rank":125,"weeks_on_chart":98},{"name":"Pink Venom","artist":"BLACKPINK","image":"https://charts-static.billboard.com/img/2022/09/blackpink-l5z-pinkvenom-t5p-180x180.jpg","rank":190,"last_week_rank":null,"peak_rank":1,"weeks_on_chart":28},{"name":"Thunder","artist":"Imagine Dragons","image":"https://charts-static.billboard.com/img/2017/05/imagine-dragons-ud7-thunder-5sq-180x180.jpg","rank":191,"last_week_rank":192,"peak_rank":167,"weeks_on_chart":46},{"name":"If We Ever Broke Up","artist":"Mae Stephens","image":"https://charts-static.billboard.com/img/2023/03/maestephens-000-ifweeverbrokeup-g5j-180x180.jpg","rank":192,"last_week_rank":195,"peak_rank":175,"weeks_on_chart":5},{"name":"Dance Monkey","artist":"Tones And I","image":"https://charts-static.billboard.com/img/2019/08/tones-and-i-e1q-dance-monkey-pbf-180x180.jpg","rank":193,"last_week_rank":163,"peak_rank":16,"weeks_on_chart":131},{"name":"The Real Slim Shady","artist":"Eminem","image":"https://charts-static.billboard.com/img/2012/07/eminem-6zg-the-real-slim-shady-cbz-180x180.jpg","rank":194,"last_week_rank":178,"peak_rank":59,"weeks_on_chart":60},{"name":"Hype Boy","artist":"NewJeans","image":"https://charts-static.billboard.com/img/2022/08/newjeans-9dv-180x180.jpg","rank":195,"last_week_rank":155,"peak_rank":52,"weeks_on_chart":37},{"name":"Moscow Mule","artist":"Bad Bunny","image":"https://charts-static.billboard.com/img/2016/10/bad-bunny-c3m-180x180.jpg","rank":196,"last_week_rank":null,"peak_rank":2,"weeks_on_chart":49},{"name":"In Da Club","artist":"50 Cent","image":"https://charts-static.billboard.com/img/2022/02/50-cent-4gk-in-da-club-znh-180x180.jpg","rank":197,"last_week_rank":190,"peak_rank":44,"weeks_on_chart":53},{"name":"Lose Yourself","artist":"Eminem","image":"https://charts-static.billboard.com/img/2010/01/eminem-6zg-lose-yourself-48q-180x180.jpg","rank":198,"last_week_rank":null,"peak_rank":25,"weeks_on_chart":55},{"name":"Do I Wanna Know?","artist":"Arctic Monkeys","image":"https://charts-static.billboard.com/img/2013/07/arctic-monkeys-4ey-doiwannaknowX-5cm-180x180.jpg","rank":199,"last_week_rank":null,"peak_rank":119,"weeks_on_chart":38},{"name":"Romantic Homicide","artist":"d4vd","image":"https://charts-static.billboard.com/img/2022/09/d4vd-7p1-romantichomicide-i6e-180x180.jpg","rank":200,"last_week_rank":176,"peak_rank":35,"weeks_on_chart":33}]}