{"date":"2026-06-23","data":[{"name":"De Lejitos","artist":"Jay Wheeler","image":"","rank":1,"last_week_rank":1,"peak_rank":0,"weeks_on_chart":7},{"name":"Dichavate","artist":"Ya Ice Dilan X Rey Tony X Helabusador","image":"","rank":2,"last_week_rank":2,"peak_rank":0,"weeks_on_chart":9},{"name":"Swim","artist":"BTS","image":"","rank":3,"last_week_rank":1,"peak_rank":0,"weeks_on_chart":13},{"name":"Dai Dai (FIFA World Cup Official Song 2026)","artist":"Shakira X Burna Boy","image":"","rank":4,"last_week_rank":4,"peak_rank":0,"weeks_on_chart":2},{"name":"Koko","artist":"Omar Courtz","image":"https://charts-static.billboard.com/img/2021/03/omarcourtz-pgl-180x180.jpg","rank":5,"last_week_rank":1,"peak_rank":0,"weeks_on_chart":16},{"name":"Cuando No Era Cantante (Remix)","artist":"Bogueto, Fuerza Regida, Anuel AA & Yung Beef","image":"https://charts-static.billboard.com/img/2026/01/elbogueto-000-cuandonoeracantanteremix-75m-180x180.jpg","rank":6,"last_week_rank":4,"peak_rank":0,"weeks_on_chart":24},{"name":"Coqueta","artist":"Fuerza Regida & Grupo Frontera","image":"https://charts-static.billboard.com/img/2018/06/fuerzaregida-1nc-180x180.jpg","rank":7,"last_week_rank":3,"peak_rank":0,"weeks_on_chart":57},{"name":"Yogurcito","artist":"Blessd","image":"https://charts-static.billboard.com/img/2021/11/blessd-j9z-180x180.jpg","rank":8,"last_week_rank":1,"peak_rank":0,"weeks_on_chart":43},{"name":"Baile Inolvidable","artist":"Bad Bunny","image":"https://charts-static.billboard.com/img/2016/10/bad-bunny-74k-180x180.jpg","rank":9,"last_week_rank":1,"peak_rank":0,"weeks_on_chart":76},{"name":"Billie Jean","artist":"Michael Jackson","image":"https://charts-static.billboard.com/img/2009/07/michael-jackson-y4h-billiejean-u1v-180x180.jpg","rank":10,"last_week_rank":3,"peak_rank":0,"weeks_on_chart":8},{"name":"Tiroteo","artist":"Marc Segui & Pol Granch & Rauw Alejandro","image":"https://charts-static.billboard.com/img/2021/07/marcsegui-000-tiroteo-0im-180x180.jpg","rank":11,"last_week_rank":9,"peak_rank":0,"weeks_on_chart":26},{"name":"La Plena (W Sound 05)","artist":"W Sound, Beele & Ovy On The Drums","image":"https://charts-static.billboard.com/img/2025/03/wsound-000-laplenawsound05-hou-180x180.jpg","rank":12,"last_week_rank":1,"peak_rank":0,"weeks_on_chart":69},{"name":"Me Rehuso","artist":"Danny Ocean","image":"https://charts-static.billboard.com/img/2017/08/danny-ocean-z1u-merehuso-z3g-180x180.jpg","rank":13,"last_week_rank":10,"peak_rank":0,"weeks_on_chart":28},{"name":"La Villa","artist":"Ryan Castro, Kapo & Gangsta","image":"https://charts-static.billboard.com/img/2021/07/ryancastro-cv0-180x180.jpg","rank":14,"last_week_rank":1,"peak_rank":0,"weeks_on_chart":25},{"name":"Chevere (joeson_type_beat)","artist":"ARIA VEGA","image":"https://www.billboard.com/wp-content/themes/vip/pmc-billboard-2021/assets/public/lazyload-fallback.gif","rank":15,"last_week_rank":4,"peak_rank":0,"weeks_on_chart":17},{"name":"Doma","artist":"Josean Log","image":"https://www.billboard.com/wp-content/themes/vip/pmc-billboard-2021/assets/public/lazyload-fallback.gif","rank":16,"last_week_rank":16,"peak_rank":0,"weeks_on_chart":2},{"name":"Te Entiendo","artist":"Maisak x Feid x Maluma","image":"https://charts-static.billboard.com/img/2026/05/maisak-kdj-teentiendo-r5i-180x180.jpg","rank":17,"last_week_rank":6,"peak_rank":0,"weeks_on_chart":7},{"name":"EOO","artist":"Bad Bunny","image":"https://charts-static.billboard.com/img/2016/10/bad-bunny-74k-180x180.jpg","rank":18,"last_week_rank":2,"peak_rank":0,"weeks_on_chart":73},{"name":"Tu Vas Sin (Fav)","artist":"Rels B","image":"https://www.billboard.com/wp-content/themes/vip/pmc-billboard-2021/assets/public/lazyload-fallback.gif","rank":19,"last_week_rank":3,"peak_rank":0,"weeks_on_chart":47},{"name":"Tu Sancho","artist":"Fuerza Regida","image":"https://charts-static.billboard.com/img/2018/06/fuerzaregida-1nc-180x180.jpg","rank":20,"last_week_rank":6,"peak_rank":0,"weeks_on_chart":10},{"name":"Todo Lo Fue","artist":"Lenin Ramirez","image":"https://charts-static.billboard.com/img/2015/11/lenin-ramirez-abq-180x180.jpg","rank":21,"last_week_rank":21,"peak_rank":0,"weeks_on_chart":3},{"name":"444","artist":"Yan Block & Panda Black","image":"https://charts-static.billboard.com/img/2025/11/yanblock-ulr-444-wht-180x180.jpg","rank":22,"last_week_rank":6,"peak_rank":0,"weeks_on_chart":12},{"name":"Por Si Manana No Estoy","artist":"Omar Courtz","image":"https://charts-static.billboard.com/img/2021/03/omarcourtz-pgl-180x180.jpg","rank":23,"last_week_rank":13,"peak_rank":0,"weeks_on_chart":15},{"name":"Dano","artist":"Peso Pluma & Tito Double P","image":"https://charts-static.billboard.com/img/2022/04/pesopluma-axe-180x180.jpg","rank":24,"last_week_rank":24,"peak_rank":0,"weeks_on_chart":1},{"name":"Encantadora","artist":"Yandel","image":"https://charts-static.billboard.com/img/2003/09/yandel-fqk-180x180.jpg","rank":25,"last_week_rank":25,"peak_rank":0,"weeks_on_chart":1}]}